{
  "bill_id": "PRC_G2S1F1G1R2V4A1Y6T5X9M4J9P2J6H1",
  "bill_no": "2113656",
  "id_master": 198010,
  "session": 21,
  "name": "자유무역지역의 지정 및 운영에 관한 법률 일부개정법률안(대안)",
  "summary": "대안의 제안이유\n  자유무역지역에의 입주계약 해지 관련 결격사유 제도를 합리적으로 개선하고, 국민생활 및 기업활동과 밀접하게 관련 있는 신고 민원의 처리 절차를 법령에서 명확하게 규정함으로써 관련 민원의 투명하고 신속한 처리와 일선 행정기관의 적극행정을 유도하는 한편, \n  자유무역지역에서 통관을 위한 필수 절차 및 특례 등에 관한 「관세법」의 규정이 적용되도록 하고, 해외 진출기업의 국내 복귀를 적극 지원하기 위하여 외국인투자기업 외에도 자유무역지역에 입주한 비수도권 국내복귀기업에 대해서도 임대료를 감면할 수 있도록 하며, 전자상거래 활성화 등을 위하여 입주기업체가 물품을 분할하거나 병합하여 재고관리를 할 수 있도록 하는 등 현행 제도의 운영상 나타난 일부 미비점을 개선ㆍ보완하려는 것임.\n\n대안의 주요내용\n가. 자유무역지역에서 「관세법」에 따른 절차 규정의 적용(안 제3조제1항제2호 및 제3호 신설)\n  자유무역지역에서는 원칙적으로 「관세법」을 적용하지 아니하도록 하고 있으나, 관행상 적용되어 온 「관세법」상 입출항ㆍ하역 절차 등 통관을 위하여 필수적인 절차에 관한 규정이 적용됨을 명확히 하고, 물품의 통관에 관하여 입주기업체에게 유리한 「관세법」상 규정이 적용되도록 함.\n나. 피성년후견인 관련 결격사유 제도 합리화(안 제12조제8호)\n  피성년후견인임을 이유로 자유무역지역에의 입주계약이 해지된 경우에 그 해지된 후 2년이 지나지 아니한 자는 입주계약을 체결할 수 없도록 하던 것을, 앞으로는 해당 결격사유가 해소된 때에는 바로 입주계약을 체결할 수 있도록 함.\n다. 신고 민원의 처리절차 명확화(안 제14조제5항, 제29조제2항, 제30조제2항, 제35조제4항 및 제38조제4항 신설)\n  자유무역지역 내 제조업종 외 사업의 사업개시 신고, 물품의 자유무역지역 내 반입신고, 외국물품 등의 자유무역지역에서 국외로의 반출신고, 역외작업 공정에서 발생한 폐품의 처분신고 및 외국물품 등의 멸실ㆍ분실 등의 신고가 수리가 필요한 신고임을 명시함. \n라. 자유무역지역에서 임대료 감면대상 확대(안 제20조제1항)\n  관리권자 또는 지방자치단체의 장은 자유무역지역에 입주한 비수도권 국내복귀기업에 대해서 임대료를 감면할 수 있도록 함.\n마. 화물 재고관리 간소화 근거 마련(안 제38조제6항 신설)\n  입주기업체가 관세청장이 정하는 기준에 따른 물품의 재고관리 체계를 갖춘 경우에는 자유무역지역 안으로 반입하거나 자유무역지역으로부터 반출하는 물품, 자유무역지역에서 생산한 물품 등을 화물단위를 유지한 채 보관ㆍ사용하지 않고 개인 구매단위로 분할ㆍ병합하여 관리할 수 있도록 함.\n바. 적재기간 위반행위에 대한 과태료 상한액 하향 조정(현행 제70조제2항제7호 삭제, 안 제70조제3항제2호의2 신설)\n  외국물품 등에 대한 국외 반출신고가 수리된 후 그 적재기간을 넘겨 해당 외국물품 등을 적재한 자에 대한 과태료 상한액을 해당 위반행위의 가벌성 등을 고려하여 200만원에서 100만원으로 하향 조정함.",
  "related_bill_ids": ["PRC_U2X0J0W8V1E4T1M1I1X9K2V1T5V3R8", "PRC_X2R0Z1J2B1Q0G1I0K5L2Y5E4D1B3E1", "PRC_D2K0H0K7W0I1R1M7V2S0O2F3C3L5K3", "PRC_S2U0H1O0G1P5G1H0X5J8J2O5H7W7L7", "PRC_M2W0H0S9X0O9O1Q4X2P6J3Q9P2U0O1"],
  "proposal_date": "2021-12-01",
  "vote_date": "2021-12-02",
  "members_voting": 210,
  "members_registered": 295,
  "total_votes": 210,
  "total_agree": 208,
  "total_oppose": 0,
  "total_abstain": 2,
  "members_agree": [{
    "member_id": "9771142",
    "name": "강대식"
  }, {
    "member_id": "9771174",
    "name": "강득구"
  }, {
    "member_id": "9771233",
    "name": "강민국"
  }, {
    "member_id": "9770933",
    "name": "강병원"
  }, {
    "member_id": "9771116",
    "name": "강선우"
  }, {
    "member_id": "9771276",
    "name": "강은미"
  }, {
    "member_id": "9771168",
    "name": "강준현"
  }, {
    "member_id": "9771007",
    "name": "강훈식"
  }, {
    "member_id": "9771109",
    "name": "고민정"
  }, {
    "member_id": "9771180",
    "name": "고영인"
  }, {
    "member_id": "9770931",
    "name": "고용진"
  }, {
    "member_id": "9771224",
    "name": "구자근"
  }, {
    "member_id": "9771165",
    "name": "권명호"
  }, {
    "member_id": "9771259",
    "name": "권인숙"
  }, {
    "member_id": "9770927",
    "name": "기동민"
  }, {
    "member_id": "9771258",
    "name": "김경만"
  }, {
    "member_id": "9770712",
    "name": "김경협"
  }, {
    "member_id": "9771152",
    "name": "김교흥"
  }, {
    "member_id": "9771164",
    "name": "김기현"
  }, {
    "member_id": "9770719",
    "name": "김도읍"
  }, {
    "member_id": "9770997",
    "name": "김두관"
  }, {
    "member_id": "9770723",
    "name": "김민기"
  }, {
    "member_id": "9771173",
    "name": "김민철"
  }, {
    "member_id": "9770941",
    "name": "김병기"
  }, {
    "member_id": "9770984",
    "name": "김병욱"
  }, {
    "member_id": "9771285",
    "name": "김병욱"
  }, {
    "member_id": "9771268",
    "name": "김병주"
  }, {
    "member_id": "9770527",
    "name": "김상희"
  }, {
    "member_id": "9771208",
    "name": "김성주"
  }, {
    "member_id": "9771089",
    "name": "김성환"
  }, {
    "member_id": "9771210",
    "name": "김수흥"
  }, {
    "member_id": "9771220",
    "name": "김승남"
  }, {
    "member_id": "9771144",
    "name": "김승수"
  }, {
    "member_id": "9771169",
    "name": "김승원"
  }, {
    "member_id": "9770975",
    "name": "김영주"
  }, {
    "member_id": "9770981",
    "name": "김영진"
  }, {
    "member_id": "9770934",
    "name": "김영호"
  }, {
    "member_id": "9771186",
    "name": "김용민"
  }, {
    "member_id": "9771147",
    "name": "김용판"
  }, {
    "member_id": "9771127",
    "name": "김웅"
  }, {
    "member_id": "9771214",
    "name": "김원이"
  }, {
    "member_id": "9771206",
    "name": "김윤덕"
  }, {
    "member_id": "9771288",
    "name": "김의겸"
  }, {
    "member_id": "9771023",
    "name": "김정재"
  }, {
    "member_id": "9771090",
    "name": "김정호"
  }, {
    "member_id": "9771009",
    "name": "김종민"
  }, {
    "member_id": "9771192",
    "name": "김주영"
  }, {
    "member_id": "9770982",
    "name": "김진표"
  }, {
    "member_id": "9770986",
    "name": "김철민"
  }, {
    "member_id": "9770741",
    "name": "김태년"
  }, {
    "member_id": "9770991",
    "name": "김한정"
  }, {
    "member_id": "9771270",
    "name": "김홍걸"
  }, {
    "member_id": "9771216",
    "name": "김회재"
  }, {
    "member_id": "9770753",
    "name": "노웅래"
  }, {
    "member_id": "9771274",
    "name": "류호정"
  }, {
    "member_id": "9771091",
    "name": "맹성규"
  }, {
    "member_id": "9771187",
    "name": "문정복"
  }, {
    "member_id": "9771204",
    "name": "문진석"
  }, {
    "member_id": "9771175",
    "name": "민병덕"
  }, {
    "member_id": "9771159",
    "name": "민형배"
  }, {
    "member_id": "9770764",
    "name": "민홍철"
  }, {
    "member_id": "9770911",
    "name": "박광온"
  }, {
    "member_id": "9771248",
    "name": "박대수"
  }, {
    "member_id": "9770767",
    "name": "박대출"
  }, {
    "member_id": "9771193",
    "name": "박상혁"
  }, {
    "member_id": "9771107",
    "name": "박성준"
  }, {
    "member_id": "9770944",
    "name": "박성중"
  }, {
    "member_id": "9771135",
    "name": "박수영"
  }, {
    "member_id": "9771162",
    "name": "박영순"
  }, {
    "member_id": "9771030",
    "name": "박완수"
  }, {
    "member_id": "9770929",
    "name": "박용진"
  }, {
    "member_id": "9770950",
    "name": "박재호"
  }, {
    "member_id": "9770995",
    "name": "박정"
  }, {
    "member_id": "9770932",
    "name": "박주민"
  }, {
    "member_id": "9770963",
    "name": "박찬대"
  }, {
    "member_id": "9771226",
    "name": "박형수"
  }, {
    "member_id": "9770779",
    "name": "박홍근"
  }, {
    "member_id": "9771148",
    "name": "배준영"
  }, {
    "member_id": "9771277",
    "name": "배진교"
  }, {
    "member_id": "9771137",
    "name": "백종헌"
  }, {
    "member_id": "9770980",
    "name": "백혜련"
  }, {
    "member_id": "9770356",
    "name": "변재일"
  }, {
    "member_id": "9771218",
    "name": "서동용"
  }, {
    "member_id": "9771133",
    "name": "서병수"
  }, {
    "member_id": "9771092",
    "name": "서삼석"
  }, {
    "member_id": "9770784",
    "name": "서영교"
  }, {
    "member_id": "9771176",
    "name": "서영석"
  }, {
    "member_id": "9770786",
    "name": "설훈"
  }, {
    "member_id": "9771217",
    "name": "소병철"
  }, {
    "member_id": "9770999",
    "name": "소병훈"
  }, {
    "member_id": "9771093",
    "name": "송갑석"
  }, {
    "member_id": "9771094",
    "name": "송언석"
  }, {
    "member_id": "9771058",
    "name": "송옥주"
  }, {
    "member_id": "9771238",
    "name": "송재호"
  }, {
    "member_id": "9770968",
    "name": "신동근"
  }, {
    "member_id": "9771209",
    "name": "신영대"
  }, {
    "member_id": "9771219",
    "name": "신정훈"
  }, {
    "member_id": "9771257",
    "name": "신현영"
  }, {
    "member_id": "9770587",
    "name": "안규백"
  }, {
    "member_id": "9770372",
    "name": "안민석"
  }, {
    "member_id": "9771132",
    "name": "안병길"
  }, {
    "member_id": "9771017",
    "name": "안호영"
  }, {
    "member_id": "9771273",
    "name": "양경숙"
  }, {
    "member_id": "9771178",
    "name": "양기대"
  }, {
    "member_id": "9771287",
    "name": "양이원영"
  }, {
    "member_id": "9771271",
    "name": "양정숙"
  }, {
    "member_id": "9771155",
    "name": "양향자"
  }, {
    "member_id": "9771010",
    "name": "어기구"
  }, {
    "member_id": "9771113",
    "name": "오기형"
  }, {
    "member_id": "9771172",
    "name": "오영환"
  }, {
    "member_id": "9771037",
    "name": "오영훈"
  }, {
    "member_id": "9771261",
    "name": "용혜인"
  }, {
    "member_id": "9770872",
    "name": "우원식"
  }, {
    "member_id": "9771038",
    "name": "위성곤"
  }, {
    "member_id": "9771121",
    "name": "유기홍"
  }, {
    "member_id": "9770966",
    "name": "유동수"
  }, {
    "member_id": "9771199",
    "name": "유상범"
  }, {
    "member_id": "9770912",
    "name": "유의동"
  }, {
    "member_id": "9771266",
    "name": "유정주"
  }, {
    "member_id": "9771118",
    "name": "윤건영"
  }, {
    "member_id": "9770808",
    "name": "윤관석"
  }, {
    "member_id": "9771263",
    "name": "윤미향"
  }, {
    "member_id": "9771153",
    "name": "윤영덕"
  }, {
    "member_id": "9771170",
    "name": "윤영찬"
  }, {
    "member_id": "9771221",
    "name": "윤재갑"
  }, {
    "member_id": "9770812",
    "name": "윤재옥"
  }, {
    "member_id": "9771239",
    "name": "윤주경"
  }, {
    "member_id": "9771212",
    "name": "윤준병"
  }, {
    "member_id": "9771240",
    "name": "윤창현"
  }, {
    "member_id": "9770876",
    "name": "윤호중"
  }, {
    "member_id": "9770813",
    "name": "윤후덕"
  }, {
    "member_id": "9770905",
    "name": "이개호"
  }, {
    "member_id": "9771260",
    "name": "이동주"
  }, {
    "member_id": "9771028",
    "name": "이만희"
  }, {
    "member_id": "9771154",
    "name": "이병훈"
  }, {
    "member_id": "9770414",
    "name": "이상민"
  }, {
    "member_id": "9771207",
    "name": "이상직"
  }, {
    "member_id": "9771098",
    "name": "이상헌"
  }, {
    "member_id": "9771151",
    "name": "이성만"
  }, {
    "member_id": "9771185",
    "name": "이소영"
  }, {
    "member_id": "9771269",
    "name": "이수진"
  }, {
    "member_id": "9771251",
    "name": "이영"
  }, {
    "member_id": "9771158",
    "name": "이용빈"
  }, {
    "member_id": "9771115",
    "name": "이용선"
  }, {
    "member_id": "9771184",
    "name": "이용우"
  }, {
    "member_id": "9770826",
    "name": "이원욱"
  }, {
    "member_id": "9771213",
    "name": "이원택"
  }, {
    "member_id": "9771201",
    "name": "이장섭"
  }, {
    "member_id": "9771060",
    "name": "이재정"
  }, {
    "member_id": "9771205",
    "name": "이정문"
  }, {
    "member_id": "9770914",
    "name": "이종배"
  }, {
    "member_id": "9771242",
    "name": "이종성"
  }, {
    "member_id": "9771138",
    "name": "이주환"
  }, {
    "member_id": "9771002",
    "name": "이철규"
  }, {
    "member_id": "9771190",
    "name": "이탄희"
  }, {
    "member_id": "9770836",
    "name": "이학영"
  }, {
    "member_id": "9771129",
    "name": "이해식"
  }, {
    "member_id": "9770837",
    "name": "이헌승"
  }, {
    "member_id": "9771157",
    "name": "이형석"
  }, {
    "member_id": "9770839",
    "name": "인재근"
  }, {
    "member_id": "9771041",
    "name": "임이자"
  }, {
    "member_id": "9771000",
    "name": "임종성"
  }, {
    "member_id": "9771203",
    "name": "임호선"
  }, {
    "member_id": "9771160",
    "name": "장철민"
  }, {
    "member_id": "9771275",
    "name": "장혜영"
  }, {
    "member_id": "9771139",
    "name": "전봉민"
  }, {
    "member_id": "9771272",
    "name": "전용기"
  }, {
    "member_id": "9770951",
    "name": "전재수"
  }, {
    "member_id": "9771140",
    "name": "정동만"
  }, {
    "member_id": "9771012",
    "name": "정운천"
  }, {
    "member_id": "9771150",
    "name": "정일영"
  }, {
    "member_id": "9771103",
    "name": "정점식"
  }, {
    "member_id": "9771068",
    "name": "정춘숙"
  }, {
    "member_id": "9771122",
    "name": "정태호"
  }, {
    "member_id": "9771264",
    "name": "정필모"
  }, {
    "member_id": "9771229",
    "name": "정희용"
  }, {
    "member_id": "9770450",
    "name": "조경태"
  }, {
    "member_id": "9770973",
    "name": "조승래"
  }, {
    "member_id": "9771156",
    "name": "조오섭"
  }, {
    "member_id": "9770990",
    "name": "조응천"
  }, {
    "member_id": "9770456",
    "name": "조정식"
  }, {
    "member_id": "9771244",
    "name": "조태용"
  }, {
    "member_id": "9771215",
    "name": "주철현"
  }, {
    "member_id": "9770883",
    "name": "주호영"
  }, {
    "member_id": "9771250",
    "name": "지성호"
  }, {
    "member_id": "9770852",
    "name": "진선미"
  }, {
    "member_id": "9771117",
    "name": "진성준"
  }, {
    "member_id": "9771282",
    "name": "최강욱"
  }, {
    "member_id": "9771119",
    "name": "최기상"
  }, {
    "member_id": "9771252",
    "name": "최승재"
  }, {
    "member_id": "9770952",
    "name": "최인호"
  }, {
    "member_id": "9771188",
    "name": "최종윤"
  }, {
    "member_id": "9771267",
    "name": "최혜영"
  }, {
    "member_id": "9770962",
    "name": "추경호"
  }, {
    "member_id": "9771286",
    "name": "태영호"
  }, {
    "member_id": "9771234",
    "name": "하영제"
  }, {
    "member_id": "9771241",
    "name": "한무경"
  }, {
    "member_id": "9771211",
    "name": "한병도"
  }, {
    "member_id": "9771182",
    "name": "한준호"
  }, {
    "member_id": "9771196",
    "name": "허영"
  }, {
    "member_id": "9771149",
    "name": "허종식"
  }, {
    "member_id": "9771146",
    "name": "홍석준"
  }, {
    "member_id": "9771167",
    "name": "홍성국"
  }, {
    "member_id": "9770676",
    "name": "홍영표"
  }, {
    "member_id": "9770864",
    "name": "홍익표"
  }, {
    "member_id": "9771183",
    "name": "홍정민"
  }, {
    "member_id": "9771130",
    "name": "황보승희"
  }, {
    "member_id": "9771161",
    "name": "황운하"
  }],
  "members_oppose": [],
  "members_abstain": [{
    "member_id": "9771283",
    "name": "강민정"
  }, {
    "member_id": "9771001",
    "name": "송기헌"
  }],
  "result": "원안가결",
  "kind": "법률안",
  "committee": "산업통상자원중소벤처기업위원회"
}