{
  "bill_id": "PRC_G1D7O0F3X2L3A1P3S0D9R5N2K4K3B2",
  "bill_no": "2006479",
  "id_master": 110928,
  "session": 20,
  "name": "건축법 일부개정법률안(대안)",
  "summary": "■ 제안이유 \n 신고 민원의 투명하고 신속한 처리와 일선 행정기관의 적극행정을 유도하기 위하여 건축신고, 신고사항의 변경신고 및 가설건축물의 축조신고에 대하여 신고수리 여부 통지를 의무화하고, 건축물의 착공신고에 대해서는 신고수리 여부 통지와 함께 통지 기한 내에 통지를 하지 않은 경우 신고를 수리한 것으로 간주(看做)하는 제도를 도입함.\n  또한, 지역건축안전센터를 설립하여 허가권자의 건축허가, 공사감리 등에 대한 관리·감독 업무 등을 지원할 수 있도록 하고, 지역건축안전센터의 안정적 운영을 위하여 건축안전특별회계를 설치하는 등 지방자치단체의 건축물 안전에 대한 전문적인 관리체계를 마련하고자 함.\n 아울러, 건축물 노후화 등으로 신규 건축 수요가 있는 도시재생활성화지역을 조례 개정 없이도 건축협정을 체결할 수 있는 건축협정 가능구역에 포함시키고, 건축협정 집중구역을 지정하여 건축협정이 보다 효과적이고 계획적으로 이루어질 수 있게 하려는 것임.\n\n■ 주요내용 \n가. 건축신고 등의 신고수리 여부 통지(안 제14조제3항？제4항, 제16조제4항, 제20조제4항 신설)\n    건축신고, 신고사항의 변경, 가설건축물의 축조신고를 받은 경우 관계 행정기관과의 협의 등이 필요하지 않은 경우에는 5일 이내, 협의 등이 필요한 경우에는 20일 이내에 신고수리 여부 및 처리기간의 연장 여부를 신고인에게 통지하도록 함.\n나. 건축물의 착공신고의 신고수리 통지 및 수리 간주제 도입(안 제21조제3항 및 제4항 신설)\n    건축물의 착공신고를 받은 경우에는 3일 이내에 신고수리 여부 및 처리기간 연장 여부를 신고인에게 통지하도록 하고, 해당 기간 내에 신고수리 여부나 처리기간의 연장 여부를 통지하지 않으면 신고를 수리한 것으로 간주함.\n다. 「도시재생 활성화 및 지원에 관한 특별법」에 따른 도시재생활성화지역을 건축협정 가능구역에 추가함(안 제77조의4제1항제4호 신설)\n라. 효과적이고 계획적인 건축협정을 유도를 위하여 건축협정 집중구역을 지정할 수 있도록 함(안 제77조의14 신설)\n마. 지역건축안전센터의 설립 및 건축안전특별회계 설치(안 제87조의2 및 제87조의3 신설)\n    지방자치단체별로 지역건축안전센터를 설립하여 허가권자의 건축허가, 공사감리 등에 대한 관리·감독 업무 등을 지원할 수 있도록  하고, 지역건축안전센터의 안정적 운영을 위하여 건축안전특별회계를 설치할 수 있도록 함.\n바. 지역건축안전센터의 전문인력에 대하여 「형법」 등의 벌칙 적용시 공무원으로 의제함(안 제105조제5호 신설)\n사. 지역건축안전센터의 전문인력이 건축허가, 안전점검 등을 허위로 보고？점검 등을 한 경우에는 2년 이하 징역 또는 2억원 이하의 벌금에 처함(안 제109조제2호 신설)",
  "related_bill_ids": ["ARC_L1P6Z1A2D2M8P1I3F3N5V2P6B3X5B2", "PRC_O1J7N0O1C0H5B1N1I1V7O4Y0G0Y1V3", "PRC_Q1V6V1Z2Z3X0F1S7S3A1L4N0H8K4G5"],
  "proposal_date": "2017-03-29",
  "vote_date": "2017-03-30",
  "members_voting": 181,
  "members_registered": 299,
  "total_votes": 181,
  "total_agree": 171,
  "total_oppose": 2,
  "total_abstain": 8,
  "members_agree": [{
    "member_id": "9770933",
    "name": "강병원"
  }, {
    "member_id": "9770279",
    "name": "강창일"
  }, {
    "member_id": "9771007",
    "name": "강훈식"
  }, {
    "member_id": "9770931",
    "name": "고용진"
  }, {
    "member_id": "9770956",
    "name": "곽상도"
  }, {
    "member_id": "9771066",
    "name": "권미혁"
  }, {
    "member_id": "9770998",
    "name": "권칠승"
  }, {
    "member_id": "9770937",
    "name": "금태섭"
  }, {
    "member_id": "9770927",
    "name": "기동민"
  }, {
    "member_id": "9770712",
    "name": "김경협"
  }, {
    "member_id": "9770713",
    "name": "김관영"
  }, {
    "member_id": "9770523",
    "name": "김광림"
  }, {
    "member_id": "9771044",
    "name": "김규환"
  }, {
    "member_id": "9770716",
    "name": "김기선"
  }, {
    "member_id": "9770719",
    "name": "김도읍"
  }, {
    "member_id": "9770723",
    "name": "김민기"
  }, {
    "member_id": "9770983",
    "name": "김병관"
  }, {
    "member_id": "9770941",
    "name": "김병기"
  }, {
    "member_id": "9770960",
    "name": "김부겸"
  }, {
    "member_id": "9770725",
    "name": "김상훈"
  }, {
    "member_id": "9770930",
    "name": "김선동"
  }, {
    "member_id": "9770942",
    "name": "김성식"
  }, {
    "member_id": "9770985",
    "name": "김성원"
  }, {
    "member_id": "9770727",
    "name": "김성찬"
  }, {
    "member_id": "9771075",
    "name": "김수민"
  }, {
    "member_id": "9771053",
    "name": "김순례"
  }, {
    "member_id": "9771049",
    "name": "김승희"
  }, {
    "member_id": "9770975",
    "name": "김영주"
  }, {
    "member_id": "9770981",
    "name": "김영진"
  }, {
    "member_id": "9770949",
    "name": "김영춘"
  }, {
    "member_id": "9770934",
    "name": "김영호"
  }, {
    "member_id": "9770542",
    "name": "김용태"
  }, {
    "member_id": "9770310",
    "name": "김재경"
  }, {
    "member_id": "9770993",
    "name": "김정우"
  }, {
    "member_id": "9771083",
    "name": "김종대"
  }, {
    "member_id": "9771009",
    "name": "김종민"
  }, {
    "member_id": "9771016",
    "name": "김종회"
  }, {
    "member_id": "9770982",
    "name": "김진표"
  }, {
    "member_id": "9770986",
    "name": "김철민"
  }, {
    "member_id": "9770744",
    "name": "김한표"
  }, {
    "member_id": "9770953",
    "name": "김해영"
  }, {
    "member_id": "9771061",
    "name": "김현권"
  }, {
    "member_id": "9770746",
    "name": "김현미"
  }, {
    "member_id": "9771055",
    "name": "김현아"
  }, {
    "member_id": "9770753",
    "name": "노웅래"
  }, {
    "member_id": "9770755",
    "name": "도종환"
  }, {
    "member_id": "9771062",
    "name": "문미옥"
  }, {
    "member_id": "9770084",
    "name": "문희상"
  }, {
    "member_id": "9770964",
    "name": "민경욱"
  }, {
    "member_id": "9770761",
    "name": "민병두"
  }, {
    "member_id": "9770764",
    "name": "민홍철"
  }, {
    "member_id": "9771056",
    "name": "박경미"
  }, {
    "member_id": "9770911",
    "name": "박광온"
  }, {
    "member_id": "9770767",
    "name": "박대출"
  }, {
    "member_id": "9770908",
    "name": "박맹우"
  }, {
    "member_id": "9770090",
    "name": "박병석"
  }, {
    "member_id": "9771030",
    "name": "박완수"
  }, {
    "member_id": "9770774",
    "name": "박완주"
  }, {
    "member_id": "9770929",
    "name": "박용진"
  }, {
    "member_id": "9770995",
    "name": "박정"
  }, {
    "member_id": "9770932",
    "name": "박주민"
  }, {
    "member_id": "9771071",
    "name": "박주현"
  }, {
    "member_id": "9770963",
    "name": "박찬대"
  }, {
    "member_id": "9770779",
    "name": "박홍근"
  }, {
    "member_id": "9771025",
    "name": "백승주"
  }, {
    "member_id": "9770573",
    "name": "백재현"
  }, {
    "member_id": "9770356",
    "name": "변재일"
  }, {
    "member_id": "9771035",
    "name": "서형수"
  }, {
    "member_id": "9770786",
    "name": "설훈"
  }, {
    "member_id": "9770999",
    "name": "소병훈"
  }, {
    "member_id": "9770935",
    "name": "손혜원"
  }, {
    "member_id": "9770996",
    "name": "송석준"
  }, {
    "member_id": "9771058",
    "name": "송옥주"
  }, {
    "member_id": "9770968",
    "name": "신동근"
  }, {
    "member_id": "9771069",
    "name": "신용현"
  }, {
    "member_id": "9770989",
    "name": "신창현"
  }, {
    "member_id": "9770798",
    "name": "심재권"
  }, {
    "member_id": "9770138",
    "name": "심재철"
  }, {
    "member_id": "9770372",
    "name": "안민석"
  }, {
    "member_id": "9771017",
    "name": "안호영"
  }, {
    "member_id": "9770375",
    "name": "양승조"
  }, {
    "member_id": "9771010",
    "name": "어기구"
  }, {
    "member_id": "9770802",
    "name": "염동열"
  }, {
    "member_id": "9771070",
    "name": "오세정"
  }, {
    "member_id": "9770918",
    "name": "오신환"
  }, {
    "member_id": "9771037",
    "name": "오영훈"
  }, {
    "member_id": "9770380",
    "name": "오제세"
  }, {
    "member_id": "9770871",
    "name": "우상호"
  }, {
    "member_id": "9770872",
    "name": "우원식"
  }, {
    "member_id": "9771038",
    "name": "위성곤"
  }, {
    "member_id": "9770387",
    "name": "유기준"
  }, {
    "member_id": "9770966",
    "name": "유동수"
  }, {
    "member_id": "9771050",
    "name": "유민봉"
  }, {
    "member_id": "9770874",
    "name": "유승희"
  }, {
    "member_id": "9770807",
    "name": "유은혜"
  }, {
    "member_id": "9770912",
    "name": "유의동"
  }, {
    "member_id": "9770596",
    "name": "유재중"
  }, {
    "member_id": "9770808",
    "name": "윤관석"
  }, {
    "member_id": "9770598",
    "name": "윤상현"
  }, {
    "member_id": "9771085",
    "name": "윤소하"
  }, {
    "member_id": "9770812",
    "name": "윤재옥"
  }, {
    "member_id": "9770979",
    "name": "윤종오"
  }, {
    "member_id": "9771051",
    "name": "윤종필"
  }, {
    "member_id": "9770813",
    "name": "윤후덕"
  }, {
    "member_id": "9770905",
    "name": "이개호"
  }, {
    "member_id": "9771080",
    "name": "이동섭"
  }, {
    "member_id": "9771028",
    "name": "이만희"
  }, {
    "member_id": "9770602",
    "name": "이명수"
  }, {
    "member_id": "9771072",
    "name": "이상돈"
  }, {
    "member_id": "9770414",
    "name": "이상민"
  }, {
    "member_id": "9770416",
    "name": "이석현"
  }, {
    "member_id": "9771003",
    "name": "이양수"
  }, {
    "member_id": "9770822",
    "name": "이언주"
  }, {
    "member_id": "9770824",
    "name": "이완영"
  }, {
    "member_id": "9770826",
    "name": "이원욱"
  }, {
    "member_id": "9770829",
    "name": "이장우"
  }, {
    "member_id": "9771060",
    "name": "이재정"
  }, {
    "member_id": "9770916",
    "name": "이정현"
  }, {
    "member_id": "9770194",
    "name": "이종걸"
  }, {
    "member_id": "9771040",
    "name": "이종명"
  }, {
    "member_id": "9770914",
    "name": "이종배"
  }, {
    "member_id": "9770499",
    "name": "이주영"
  }, {
    "member_id": "9770835",
    "name": "이채익"
  }, {
    "member_id": "9771063",
    "name": "이철희"
  }, {
    "member_id": "9770623",
    "name": "이춘석"
  }, {
    "member_id": "9770836",
    "name": "이학영"
  }, {
    "member_id": "9770837",
    "name": "이헌승"
  }, {
    "member_id": "9770939",
    "name": "이훈"
  }, {
    "member_id": "9770839",
    "name": "인재근"
  }, {
    "member_id": "9771000",
    "name": "임종성"
  }, {
    "member_id": "9771079",
    "name": "장정숙"
  }, {
    "member_id": "9770954",
    "name": "장제원"
  }, {
    "member_id": "9770846",
    "name": "전해철"
  }, {
    "member_id": "9770946",
    "name": "전현희"
  }, {
    "member_id": "9770926",
    "name": "전혜숙"
  }, {
    "member_id": "9770439",
    "name": "정갑윤"
  }, {
    "member_id": "9771013",
    "name": "정동영"
  }, {
    "member_id": "9770881",
    "name": "정성호"
  }, {
    "member_id": "9770928",
    "name": "정양석"
  }, {
    "member_id": "9770907",
    "name": "정용기"
  }, {
    "member_id": "9771012",
    "name": "정운천"
  }, {
    "member_id": "9770965",
    "name": "정유섭"
  }, {
    "member_id": "9770988",
    "name": "정재호"
  }, {
    "member_id": "9770957",
    "name": "정종섭"
  }, {
    "member_id": "9771006",
    "name": "정진석"
  }, {
    "member_id": "9771068",
    "name": "정춘숙"
  }, {
    "member_id": "9771064",
    "name": "제윤경"
  }, {
    "member_id": "9770450",
    "name": "조경태"
  }, {
    "member_id": "9770973",
    "name": "조승래"
  }, {
    "member_id": "9770648",
    "name": "조원진"
  }, {
    "member_id": "9770456",
    "name": "조정식"
  }, {
    "member_id": "9771052",
    "name": "조훈현"
  }, {
    "member_id": "9770992",
    "name": "주광덕"
  }, {
    "member_id": "9770458",
    "name": "주승용"
  }, {
    "member_id": "9770883",
    "name": "주호영"
  }, {
    "member_id": "9770852",
    "name": "진선미"
  }, {
    "member_id": "9771074",
    "name": "채이배"
  }, {
    "member_id": "9770920",
    "name": "천정배"
  }, {
    "member_id": "9771027",
    "name": "최교일"
  }, {
    "member_id": "9770948",
    "name": "최명길"
  }, {
    "member_id": "9771043",
    "name": "최연혜"
  }, {
    "member_id": "9771059",
    "name": "최운열"
  }, {
    "member_id": "9770952",
    "name": "최인호"
  }, {
    "member_id": "9770994",
    "name": "표창원"
  }, {
    "member_id": "9770858",
    "name": "하태경"
  }, {
    "member_id": "9770860",
    "name": "함진규"
  }, {
    "member_id": "9770676",
    "name": "홍영표"
  }, {
    "member_id": "9770959",
    "name": "홍의락"
  }, {
    "member_id": "9770864",
    "name": "홍익표"
  }, {
    "member_id": "9770665",
    "name": "홍일표"
  }, {
    "member_id": "9770936",
    "name": "황희"
  }],
  "members_oppose": [{
    "member_id": "9771023",
    "name": "김정재"
  }, {
    "member_id": "9771034",
    "name": "엄용수"
  }],
  "members_abstain": [{
    "member_id": "9771054",
    "name": "강효상"
  }, {
    "member_id": "9770961",
    "name": "곽대훈"
  }, {
    "member_id": "9770765",
    "name": "박남춘"
  }, {
    "member_id": "9771039",
    "name": "송희경"
  }, {
    "member_id": "9770587",
    "name": "안규백"
  }, {
    "member_id": "9770878",
    "name": "이인영"
  }, {
    "member_id": "9771026",
    "name": "장석춘"
  }, {
    "member_id": "9771047",
    "name": "전희경"
  }],
  "result": "원안가결",
  "kind": "법률안",
  "committee": "국토교통위원회"
}