{
  "bill_id": "PRC_P1A7B0T6U0P1M1N5C4H7M3G4R9F3J2",
  "bill_no": "2007173",
  "id_master": 172284,
  "session": 20,
  "name": "해양폐기물 및 해양오염퇴적물 관리법안",
  "summary": "■ 제안이유 및 주요내용 \n\n\n제안이유\n\n  해양폐기물 및 해양오염퇴적물은 해양환경오염의 주요 원인으로서 그로 인한 피해가 꾸준히 증가하고 있으나 체계적 관리체계 부재로 개별적인 피해사례에 대한 단편적인 대응에 그치고 있는 실정임.\n  「해양환경관리법」에서 해양폐기물 등의 관리와 관련하여 규정하고 있으나, 다른 법률의 유사규정을 임의적으로 준용하거나 상황에 따라 필요한 규정들이 산발적으로 삽입됨에 따라 법률의 명확한 적용과 해석에 혼란을 야기하고 있음.\n  이에 해양폐기물 및 해양오염퇴적물의 관리에 관한 법률을 제정하여 해양폐기물 등의 발생을 억제하는 한편, 해양의 특수성을 반영한 수거·처리 및 재활용 방법을 도입하는 등 해양폐기물 및 해양오염퇴적물에 대한 독자적인 관리체계를 구축함으로써 해양환경을 보전하고 국민의 삶의 질 향상에 이바지하고자 하는 것임.\n\n\n\n주요내용\n\n가. 이 법은 해양폐기물 및 해양오염퇴적물을 안전하고 효율적으로 관리하는 데에 필요한 사항을 규정함으로써 해양환경의 보전 및 국민\n  의 삶의 질 향상에 이바지하는 것을 목적으로 함(안 제1조).\n나. 해양수산부장관은 관계 중앙행정기관의 장과 협의하여 해양폐기물및 해양오염퇴적물 관리 기본계획을 10년마다 수립·시행하고, 그 기본계획에 따라 해역관리청은 연차별 시행계획을 수립·시행하도록 함(안 제5조).\n다. 폐기물의 해양배출을 원칙적으로 금지하고, 다음과 같은 예외적인 경우에 허용하도록 함(안 제7조부터 제10조까지).\n  1) 육상에서 처리가 곤란한 폐기물로서 대통령령으로 정하는 폐기물에 한하여 해양수산부장관에게 신고하고 지정해역에서 배출하는 경우\n  2) 자연재해 및 사고 등으로 인하여 폐기물을 해양에 배출하고 해역관리청에 보고하는 경우\n  3) 「공유수면 관리 및 매립에 관한 법률」 제28조 및 같은 법 제35조에 따라 매립하려는 장소에 배출하는 경우\n  4) 해양수산부장관의 허가를 받아 해저면의 함몰지에 폐기물을 넣고 고립처분 하는 경우\n  5) 해양수산부장관의 허가를 받아 이산화탄소 스트림을 해양지중저장하는 경우\n라. 해양폐기물의 수거를 규정함(안 제12조부터 제14조까지).\n  1) 시장·군수·구청장이 해안폐기물을 수거하도록 하되, 해안폐기물의  발생원인이 된 행위를 한 자에게 해안폐기물의 전부 또는 일부의  수거를 명할 수 있도록 함.\n  2) 해역관리청이 부유폐기물을 수거하도록 하되, 부유폐기물의 발생원인이 된 행위를 한 자에게 부유폐기물의 전부 또는 일부의 수거를 명할 수 있도록 함.\n  3) 해양수산부장관이 침적폐기물을 수거하도록 하되, 침적폐기물의 발생원인이 된 행위를 한 자에게 침적폐기물의 전부 또는 일부의  수거를 명할 수 있도록 함.\n마. 해양수산부장관이 해양오염퇴적물을 정화하도록 하되, 해양오염퇴적물의 발생원인이 된 행위를 한 자에게 해양오염퇴적물의 전부 또는 일부를 정화할 것을 명할 수 있도록 함(안 제16조).\n바. 해양수산부령으로 정하는 기준에 적합한 해양폐기물 및 해양오염퇴적물은 습지 조성 및 복원 등의 용도로 유효활용할 수 있도록 함(안 제18조).\n사. 해양환경에 해로운 영향을 줄이기 위하여 철분 등의 물질을 해양에 살포하거나 놓아두는 등의 해양배치를 하려는 자는 해양수산부장관의 허가를 받도록 함(안 제19조).\n아. 폐기물해양배출업, 침적폐기물수거업, 해양오염퇴적물정화업 등 해양폐기물관리업을 영위하려는 자는 해양수산부장관에게 등록하도록함(안 제20조). \n자. 해양폐기물관리업자는 처리실적서를 작성하여 해양수산부장관에게제출하여야 하고, 처리대장을 작성하여 해당 선박 또는 시설에 비치하여야 하며, 폐기물해양배출업자는 폐기물인계·인수서를 작성하여 해양수산부장관에게 제출하도록 함(안 제22조).\n차. 해양수산부장관은 해양폐기물 및 해양오염퇴적물의 효율적 관리를위하여 해양폐기물 조사기관, 해양오염퇴적물 조사기관, 해양배출 검사기관을 지정할 수 있도록 함(안 제26조).\n카. 해양수산부장관은 해양폐기물 및 해양오염퇴적물의 관리에 필요한정보를 관리할 수 있는 전산처리기구를 설치·운영하도록 하고, 전자정보를 체계적이고 효율적으로 관리하기 위한 전자정보처리프로그램을 구축·운영하여야 함(안 제30조).",
  "related_bill_ids": [],
  "proposal_date": "2017-06-01",
  "vote_date": "2019-10-31",
  "members_voting": 163,
  "members_registered": 296,
  "total_votes": 163,
  "total_agree": 161,
  "total_oppose": 0,
  "total_abstain": 2,
  "members_agree": [{
    "member_id": "9770276",
    "name": "강길부"
  }, {
    "member_id": "9771036",
    "name": "강석진"
  }, {
    "member_id": "9770512",
    "name": "강석호"
  }, {
    "member_id": "9771054",
    "name": "강효상"
  }, {
    "member_id": "9771007",
    "name": "강훈식"
  }, {
    "member_id": "9770708",
    "name": "경대수"
  }, {
    "member_id": "9770931",
    "name": "고용진"
  }, {
    "member_id": "9770961",
    "name": "곽대훈"
  }, {
    "member_id": "9771066",
    "name": "권미혁"
  }, {
    "member_id": "9770998",
    "name": "권칠승"
  }, {
    "member_id": "9770937",
    "name": "금태섭"
  }, {
    "member_id": "9770927",
    "name": "기동민"
  }, {
    "member_id": "9770712",
    "name": "김경협"
  }, {
    "member_id": "9771011",
    "name": "김광수"
  }, {
    "member_id": "9770716",
    "name": "김기선"
  }, {
    "member_id": "9770719",
    "name": "김도읍"
  }, {
    "member_id": "9770295",
    "name": "김동철"
  }, {
    "member_id": "9770895",
    "name": "김무성"
  }, {
    "member_id": "9770723",
    "name": "김민기"
  }, {
    "member_id": "9770983",
    "name": "김병관"
  }, {
    "member_id": "9770941",
    "name": "김병기"
  }, {
    "member_id": "9770984",
    "name": "김병욱"
  }, {
    "member_id": "9771077",
    "name": "김삼화"
  }, {
    "member_id": "9770725",
    "name": "김상훈"
  }, {
    "member_id": "9770527",
    "name": "김상희"
  }, {
    "member_id": "9770942",
    "name": "김성식"
  }, {
    "member_id": "9771046",
    "name": "金成泰"
  }, {
    "member_id": "9771089",
    "name": "김성환"
  }, {
    "member_id": "9770534",
    "name": "김세연"
  }, {
    "member_id": "9771075",
    "name": "김수민"
  }, {
    "member_id": "9771049",
    "name": "김승희"
  }, {
    "member_id": "9770538",
    "name": "김영우"
  }, {
    "member_id": "9770975",
    "name": "김영주"
  }, {
    "member_id": "9770981",
    "name": "김영진"
  }, {
    "member_id": "9770934",
    "name": "김영호"
  }, {
    "member_id": "9770310",
    "name": "김재경"
  }, {
    "member_id": "9770993",
    "name": "김정우"
  }, {
    "member_id": "9771090",
    "name": "김정호"
  }, {
    "member_id": "9771048",
    "name": "김종석"
  }, {
    "member_id": "9771078",
    "name": "김중로"
  }, {
    "member_id": "9770986",
    "name": "김철민"
  }, {
    "member_id": "9770741",
    "name": "김태년"
  }, {
    "member_id": "9770742",
    "name": "김태흠"
  }, {
    "member_id": "9770744",
    "name": "김한표"
  }, {
    "member_id": "9770953",
    "name": "김해영"
  }, {
    "member_id": "9771055",
    "name": "김현아"
  }, {
    "member_id": "9770753",
    "name": "노웅래"
  }, {
    "member_id": "9770755",
    "name": "도종환"
  }, {
    "member_id": "9771091",
    "name": "맹성규"
  }, {
    "member_id": "9770764",
    "name": "민홍철"
  }, {
    "member_id": "9770911",
    "name": "박광온"
  }, {
    "member_id": "9770767",
    "name": "박대출"
  }, {
    "member_id": "9770770",
    "name": "박범계"
  }, {
    "member_id": "9770090",
    "name": "박병석"
  }, {
    "member_id": "9771030",
    "name": "박완수"
  }, {
    "member_id": "9770774",
    "name": "박완주"
  }, {
    "member_id": "9770776",
    "name": "박인숙"
  }, {
    "member_id": "9770995",
    "name": "박정"
  }, {
    "member_id": "9770963",
    "name": "박찬대"
  }, {
    "member_id": "9770779",
    "name": "박홍근"
  }, {
    "member_id": "9770573",
    "name": "백재현"
  }, {
    "member_id": "9770980",
    "name": "백혜련"
  }, {
    "member_id": "9770356",
    "name": "변재일"
  }, {
    "member_id": "9771092",
    "name": "서삼석"
  }, {
    "member_id": "9771035",
    "name": "서형수"
  }, {
    "member_id": "9770786",
    "name": "설훈"
  }, {
    "member_id": "9770935",
    "name": "손혜원"
  }, {
    "member_id": "9771093",
    "name": "송갑석"
  }, {
    "member_id": "9771001",
    "name": "송기헌"
  }, {
    "member_id": "9770996",
    "name": "송석준"
  }, {
    "member_id": "9771094",
    "name": "송언석"
  }, {
    "member_id": "9770967",
    "name": "송영길"
  }, {
    "member_id": "9771058",
    "name": "송옥주"
  }, {
    "member_id": "9770968",
    "name": "신동근"
  }, {
    "member_id": "9771045",
    "name": "신보라"
  }, {
    "member_id": "9770989",
    "name": "신창현"
  }, {
    "member_id": "9770798",
    "name": "심재권"
  }, {
    "member_id": "9770138",
    "name": "심재철"
  }, {
    "member_id": "9770372",
    "name": "안민석"
  }, {
    "member_id": "9770919",
    "name": "안상수"
  }, {
    "member_id": "9771017",
    "name": "안호영"
  }, {
    "member_id": "9771034",
    "name": "엄용수"
  }, {
    "member_id": "9770802",
    "name": "염동열"
  }, {
    "member_id": "9770918",
    "name": "오신환"
  }, {
    "member_id": "9770871",
    "name": "우상호"
  }, {
    "member_id": "9770592",
    "name": "원유철"
  }, {
    "member_id": "9771038",
    "name": "위성곤"
  }, {
    "member_id": "9770387",
    "name": "유기준"
  }, {
    "member_id": "9770966",
    "name": "유동수"
  }, {
    "member_id": "9771050",
    "name": "유민봉"
  }, {
    "member_id": "9770594",
    "name": "유성엽"
  }, {
    "member_id": "9770808",
    "name": "윤관석"
  }, {
    "member_id": "9770955",
    "name": "윤상직"
  }, {
    "member_id": "9771085",
    "name": "윤소하"
  }, {
    "member_id": "9770811",
    "name": "윤영석"
  }, {
    "member_id": "9771095",
    "name": "윤일규"
  }, {
    "member_id": "9771051",
    "name": "윤종필"
  }, {
    "member_id": "9771096",
    "name": "윤준호"
  }, {
    "member_id": "9771032",
    "name": "윤한홍"
  }, {
    "member_id": "9770813",
    "name": "윤후덕"
  }, {
    "member_id": "9770905",
    "name": "이개호"
  }, {
    "member_id": "9771097",
    "name": "이규희"
  }, {
    "member_id": "9771080",
    "name": "이동섭"
  }, {
    "member_id": "9771028",
    "name": "이만희"
  }, {
    "member_id": "9770602",
    "name": "이명수"
  }, {
    "member_id": "9771072",
    "name": "이상돈"
  }, {
    "member_id": "9770414",
    "name": "이상민"
  }, {
    "member_id": "9770416",
    "name": "이석현"
  }, {
    "member_id": "9771018",
    "name": "이용주"
  }, {
    "member_id": "9770826",
    "name": "이원욱"
  }, {
    "member_id": "9770972",
    "name": "이은권"
  }, {
    "member_id": "9771060",
    "name": "이재정"
  }, {
    "member_id": "9771082",
    "name": "이정미"
  }, {
    "member_id": "9770194",
    "name": "이종걸"
  }, {
    "member_id": "9770945",
    "name": "이종구"
  }, {
    "member_id": "9771040",
    "name": "이종명"
  }, {
    "member_id": "9770499",
    "name": "이주영"
  }, {
    "member_id": "9770621",
    "name": "이진복"
  }, {
    "member_id": "9770835",
    "name": "이채익"
  }, {
    "member_id": "9771002",
    "name": "이철규"
  }, {
    "member_id": "9770623",
    "name": "이춘석"
  }, {
    "member_id": "9770837",
    "name": "이헌승"
  }, {
    "member_id": "9770838",
    "name": "이현재"
  }, {
    "member_id": "9770943",
    "name": "이혜훈"
  }, {
    "member_id": "9771099",
    "name": "이후삼"
  }, {
    "member_id": "9770939",
    "name": "이훈"
  }, {
    "member_id": "9770839",
    "name": "인재근"
  }, {
    "member_id": "9771041",
    "name": "임이자"
  }, {
    "member_id": "9771000",
    "name": "임종성"
  }, {
    "member_id": "9771079",
    "name": "장정숙"
  }, {
    "member_id": "9770846",
    "name": "전해철"
  }, {
    "member_id": "9770946",
    "name": "전현희"
  }, {
    "member_id": "9770926",
    "name": "전혜숙"
  }, {
    "member_id": "9770439",
    "name": "정갑윤"
  }, {
    "member_id": "9770881",
    "name": "정성호"
  }, {
    "member_id": "9770230",
    "name": "정세균"
  }, {
    "member_id": "9770847",
    "name": "정우택"
  }, {
    "member_id": "9771012",
    "name": "정운천"
  }, {
    "member_id": "9770965",
    "name": "정유섭"
  }, {
    "member_id": "9771104",
    "name": "정은혜"
  }, {
    "member_id": "9771020",
    "name": "정인화"
  }, {
    "member_id": "9770988",
    "name": "정재호"
  }, {
    "member_id": "9771103",
    "name": "정점식"
  }, {
    "member_id": "9771068",
    "name": "정춘숙"
  }, {
    "member_id": "9770450",
    "name": "조경태"
  }, {
    "member_id": "9770973",
    "name": "조승래"
  }, {
    "member_id": "9770990",
    "name": "조응천"
  }, {
    "member_id": "9770992",
    "name": "주광덕"
  }, {
    "member_id": "9771074",
    "name": "채이배"
  }, {
    "member_id": "9770920",
    "name": "천정배"
  }, {
    "member_id": "9770976",
    "name": "최경환(국)"
  }, {
    "member_id": "9771027",
    "name": "최교일"
  }, {
    "member_id": "9771043",
    "name": "최연혜"
  }, {
    "member_id": "9771059",
    "name": "최운열"
  }, {
    "member_id": "9770952",
    "name": "최인호"
  }, {
    "member_id": "9770994",
    "name": "표창원"
  }, {
    "member_id": "9770477",
    "name": "한선교"
  }, {
    "member_id": "9770860",
    "name": "함진규"
  }, {
    "member_id": "9770676",
    "name": "홍영표"
  }, {
    "member_id": "9770864",
    "name": "홍익표"
  }, {
    "member_id": "9770665",
    "name": "홍일표"
  }],
  "members_oppose": [],
  "members_abstain": [{
    "member_id": "9771056",
    "name": "박경미"
  }, {
    "member_id": "9770962",
    "name": "추경호"
  }],
  "result": "수정가결",
  "kind": "법률안",
  "committee": "농림축산식품해양수산위원회"
}