{
  "bill_id": "PRC_P2G1S0S2G2D2A1K2X4R2V5D2Z8C9U6",
  "bill_no": "2108251",
  "id_master": 196114,
  "session": 21,
  "name": "빈집 및 소규모주택 정비에 관한 특례법 일부개정법률안",
  "summary": "제안이유\n\n  현행법에 따른 소규모주택정비사업은 가로구역에서 종전의 가로구역을 유지하면서 주거환경을 개선하거나 인접한 주민들이 주민합의체를 구성하여 소규모로 정비하는 사업으로서, 재개발사업 등 대규모 정비사업과 비교할 때 정비구역 지정, 추진위원회 구성 등의 사업 추진 절차를 생략할 수 있어 저층 노후 주거지역을 신속하게 정비할 수 있는 정비사업으로 제시되고 있음.\n  그런데, 현행법상 가로주택정비사업, 자율주택정비사업 등 소규모주택정비사업은 주거지역에서만 사업이 가능하여 역세권, 준공업지역 중 노후 건축물이 대부분인 지역 중 주거ㆍ상업ㆍ산업 등 다양한 기능이 혼재되어 있으면서 광역적 개발이 어려운 지역의 경우 소규모로 정비하는데 한계가 존재한다는 지적이 있음.\n  이에 소규모주택정비사업의 유형으로 ‘소규모재개발사업’을 도입하여 역세권, 준공업지역의 5천㎡ 미만의 소규모 지역에서 간소화된 사업 추진 절차로 노후한 지역을 신속하게 정비하여 주거환경 또는 도시환경을 개선하고자 함. \n 또한 소규모주택정비사업이 보다 실효성 있게 활발히 시행될 수 있도록, ‘소규모주택정비 관리지역’(이하 ‘관리지역’)의 개념을 도입하고자 함. 10만㎡ 이내의 관리지역에 대해서는 체계적인 소규모정비가 가능하도록 공공의 거점 소규모정비사업 및 기반시설 계획 등을 포함한 관리계획을 수립토록 함.\n  관리지역 내에서는 공공이 가로주택정비를 추진할 때 토지등소유자 2/3 이상 동의시 수용이 가능토록 하고, 자율주택정비는 주민들의 80% 이상 합의시 매도청구권을 부여하여 사업의 신속한 추진이 가능토록 소규모정비사업의 요건을 완화함. 또한, 특별건축구역 및 특별가로구역을 의제하여 보다 자유로운 건축이 가능하도록 하고, 관리계획 수립ㆍ변경시 지구단위계획ㆍ도시재생활성화계획 등이 변경되도록 의제하여 절차를 간소화 하고자함. 특히, 관리지역 내에서 가로ㆍ자율정비시 용도지역을 상향하고 법적 용적률 상한까지 건축할 수 있도록 하며, 인접한 가로주택정비사업 간 결합개발을 가능하도록 하여 소규모 정비가 보다 활발히 추진될 수 있도록 인센티브를 제공함. 이에 더하여, 관리지역 내 필요한 기반시설에 대해 국비를 지원할 수 있는 근거도 마련하여 노후한 저층 주거지에 부족한 도로ㆍ주차장 등을 적기에 확충할 수 있도록 함.\n\n\n주요내용\n\n1. 소규모 재개발 신설\n가. 역세권ㆍ준공업지역에서 소규모로 주거환경 또는 도시환경을 개선하기 위한 ‘소규모재개발사업’을 신설함(안 제2조제1항제3호라목).\n나. 소규모재개발사업은 제29조에 따라 인가받은 사업시행계획에 따라 주택 등 건축물을 건설하여 공급하는 방법으로 시행하도록 함(안 제16조제4항).\n다. 소규모재개발사업을 시행하려는 토지등소유자는 4분의 1 이상 동의를 받아 사업시행예정구역 지정을 제안할 수 있고, 시장ㆍ군수등의 사업시행예정구역 지정 고시가 있은 날부터 1년 이내에 조합설립인가 또는 공공시행자 지정 등을 하지 아니한 때에는 사업시행예정구역 지정이 취소되도록 함(안 제17조의2).\n라. 시장ㆍ군수등은 일정한 요건에 해당하는 경우 소규모재개발사업을 직접 시행하거나 토지주택공사등 공공시행자를 지정할 수 있도록 함(안 제18조).\n마. 소규모재개발사업을 시행하는 경우로서 토지등소유자가 20명 미만인 경우에는 토지등소유자의 10분의 8 이상 및 토지면적의 3분의 2 이상의 토지소유자 동의를 받아 주민합의체를 구성하도록 함(안 제22조제2항ㆍ제3항).\n바. 소규모재개발사업의 토지등소유자는 조합을 설립하는 경우 토지등소유자의 10분의 8 이상 및 토지면적의 3분의 2 이상의 토지소유자 동의를 받아 시장ㆍ군수등의 인가를 받도록 함(안 제23조제4항).\n사. 소규모재개발사업의 사업시행자는 분양신청을 하지 아니한 자 등에 대하여 「공익사업을 위한 토지 등의 취득 및 보상에 관한 법률」제3조에 따른 토지ㆍ물건 및 권리를 수용 또는 사용할 수 있도록 함(안 제35조의2).\n\n2. 소규모주택정비 관리지역 신설\n가. 노후ㆍ불량 단독주택 및 공동주택과 신축 건축물 등이 혼재하여 광역적 개발이 곤란한 지역에서 정비기반시설과 공동이용시설 확충을 통해 소규모주택정비사업을 계획적ㆍ효율적으로 추진하기 위한 ‘소규모주택정비 관리지역’(이하 ‘관리지역’)을 신설함(안 제2조제1항제9호).\n나. 공공임대주택 등을 50퍼센트 이상이 되도록 건설하는 경우, 자율주택정비사업을 1인이 시행할 수 있도록 함(안 제17조제2항).\n다. 관리지역에서 시행하는 자율주택정비사업의 경우 토지등소유자의 10분의 8 이상 및 토지면적의 3분의 2 이상의 토지소유자 동의를 받은 경우 주민합의체를 구성할 수 있도록 함(안 제22조제2항ㆍ제3항).\n라. 시장ㆍ군수등 또는 토지주택공사등이 관리지역에서 공공시행자가 가로주택정비사업을 시행하는 경우 「공익사업을 위한 토지 등의 취득 및 보상에 관한 법률」 제3조에 따른 토지ㆍ물건 및 권리를 수용 또는 사용할 수 있도록 함(안 제35조의2).\n마. 시장ㆍ군수등 또는 토지주택공사등은 관리지역에 대하여 ‘소규모주택정비 관리계획’(이하 ‘관리계획’)을 수립하여 시ㆍ도지사에게 제안할 수 있도록 함(안 제43조의2).\n바. 국가 또는 시ㆍ도지사는 시장, 군수, 자치구의 구청장 또는 토지주택공사등이 관리계획에 따라 정비기반시설 또는 공동이용시설 설치에 드는 비용의 전부 또는 일부를 보조하거나 융자할 수 있도록 함(안 제44조).\n사. 관리지역에서 시행하는 자율주택정비사업 및 가로주택정비사업에 대해 공동이용시설의 바닥면적을 「건축법」 제84조에 따른 건축물의 바닥면적에 산입하지 않으며, 서로 연접한 사업시행구역을 하나의 사업시행구역으로 통합하여 시행할 수 있도록 함(안 제48조).",
  "related_bill_ids": [],
  "proposal_date": "2021-02-23",
  "vote_date": "2021-06-29",
  "members_voting": 186,
  "members_registered": 300,
  "total_votes": 186,
  "total_agree": 164,
  "total_oppose": 3,
  "total_abstain": 19,
  "members_agree": [{
    "member_id": "9771142",
    "name": "강대식"
  }, {
    "member_id": "9771174",
    "name": "강득구"
  }, {
    "member_id": "9771233",
    "name": "강민국"
  }, {
    "member_id": "9771283",
    "name": "강민정"
  }, {
    "member_id": "9770933",
    "name": "강병원"
  }, {
    "member_id": "9771276",
    "name": "강은미"
  }, {
    "member_id": "9771168",
    "name": "강준현"
  }, {
    "member_id": "9771109",
    "name": "고민정"
  }, {
    "member_id": "9771180",
    "name": "고영인"
  }, {
    "member_id": "9770931",
    "name": "고용진"
  }, {
    "member_id": "9770956",
    "name": "곽상도"
  }, {
    "member_id": "9771224",
    "name": "구자근"
  }, {
    "member_id": "9771165",
    "name": "권명호"
  }, {
    "member_id": "9771259",
    "name": "권인숙"
  }, {
    "member_id": "9770927",
    "name": "기동민"
  }, {
    "member_id": "9771258",
    "name": "김경만"
  }, {
    "member_id": "9771152",
    "name": "김교흥"
  }, {
    "member_id": "9771164",
    "name": "김기현"
  }, {
    "member_id": "9770719",
    "name": "김도읍"
  }, {
    "member_id": "9770723",
    "name": "김민기"
  }, {
    "member_id": "9771268",
    "name": "김병주"
  }, {
    "member_id": "9770725",
    "name": "김상훈"
  }, {
    "member_id": "9770527",
    "name": "김상희"
  }, {
    "member_id": "9771208",
    "name": "김성주"
  }, {
    "member_id": "9771089",
    "name": "김성환"
  }, {
    "member_id": "9771210",
    "name": "김수흥"
  }, {
    "member_id": "9771220",
    "name": "김승남"
  }, {
    "member_id": "9771169",
    "name": "김승원"
  }, {
    "member_id": "9771111",
    "name": "김영배"
  }, {
    "member_id": "9770981",
    "name": "김영진"
  }, {
    "member_id": "9770934",
    "name": "김영호"
  }, {
    "member_id": "9771186",
    "name": "김용민"
  }, {
    "member_id": "9771147",
    "name": "김용판"
  }, {
    "member_id": "9771214",
    "name": "김원이"
  }, {
    "member_id": "9771206",
    "name": "김윤덕"
  }, {
    "member_id": "9771090",
    "name": "김정호"
  }, {
    "member_id": "9771192",
    "name": "김주영"
  }, {
    "member_id": "9770982",
    "name": "김진표"
  }, {
    "member_id": "9770986",
    "name": "김철민"
  }, {
    "member_id": "9771216",
    "name": "김회재"
  }, {
    "member_id": "9770752",
    "name": "남인순"
  }, {
    "member_id": "9770753",
    "name": "노웅래"
  }, {
    "member_id": "9770755",
    "name": "도종환"
  }, {
    "member_id": "9771141",
    "name": "류성걸"
  }, {
    "member_id": "9771274",
    "name": "류호정"
  }, {
    "member_id": "9771091",
    "name": "맹성규"
  }, {
    "member_id": "9771175",
    "name": "민병덕"
  }, {
    "member_id": "9771159",
    "name": "민형배"
  }, {
    "member_id": "9770764",
    "name": "민홍철"
  }, {
    "member_id": "9770911",
    "name": "박광온"
  }, {
    "member_id": "9771193",
    "name": "박상혁"
  }, {
    "member_id": "9771107",
    "name": "박성준"
  }, {
    "member_id": "9771135",
    "name": "박수영"
  }, {
    "member_id": "9771162",
    "name": "박영순"
  }, {
    "member_id": "9770995",
    "name": "박정"
  }, {
    "member_id": "9770963",
    "name": "박찬대"
  }, {
    "member_id": "9771226",
    "name": "박형수"
  }, {
    "member_id": "9770779",
    "name": "박홍근"
  }, {
    "member_id": "9771277",
    "name": "배진교"
  }, {
    "member_id": "9771137",
    "name": "백종헌"
  }, {
    "member_id": "9770980",
    "name": "백혜련"
  }, {
    "member_id": "9770356",
    "name": "변재일"
  }, {
    "member_id": "9771218",
    "name": "서동용"
  }, {
    "member_id": "9771166",
    "name": "서범수"
  }, {
    "member_id": "9771133",
    "name": "서병수"
  }, {
    "member_id": "9771092",
    "name": "서삼석"
  }, {
    "member_id": "9771176",
    "name": "서영석"
  }, {
    "member_id": "9771254",
    "name": "서정숙"
  }, {
    "member_id": "9770786",
    "name": "설훈"
  }, {
    "member_id": "9771217",
    "name": "소병철"
  }, {
    "member_id": "9770999",
    "name": "소병훈"
  }, {
    "member_id": "9771093",
    "name": "송갑석"
  }, {
    "member_id": "9771238",
    "name": "송재호"
  }, {
    "member_id": "9770968",
    "name": "신동근"
  }, {
    "member_id": "9771209",
    "name": "신영대"
  }, {
    "member_id": "9771219",
    "name": "신정훈"
  }, {
    "member_id": "9771257",
    "name": "신현영"
  }, {
    "member_id": "9770869",
    "name": "심상정"
  }, {
    "member_id": "9770587",
    "name": "안규백"
  }, {
    "member_id": "9770372",
    "name": "안민석"
  }, {
    "member_id": "9771017",
    "name": "안호영"
  }, {
    "member_id": "9771273",
    "name": "양경숙"
  }, {
    "member_id": "9771143",
    "name": "양금희"
  }, {
    "member_id": "9771178",
    "name": "양기대"
  }, {
    "member_id": "9771271",
    "name": "양정숙"
  }, {
    "member_id": "9771010",
    "name": "어기구"
  }, {
    "member_id": "9771113",
    "name": "오기형"
  }, {
    "member_id": "9771038",
    "name": "위성곤"
  }, {
    "member_id": "9770966",
    "name": "유동수"
  }, {
    "member_id": "9771266",
    "name": "유정주"
  }, {
    "member_id": "9771118",
    "name": "윤건영"
  }, {
    "member_id": "9770808",
    "name": "윤관석"
  }, {
    "member_id": "9771263",
    "name": "윤미향"
  }, {
    "member_id": "9771153",
    "name": "윤영덕"
  }, {
    "member_id": "9771170",
    "name": "윤영찬"
  }, {
    "member_id": "9771221",
    "name": "윤재갑"
  }, {
    "member_id": "9771212",
    "name": "윤준병"
  }, {
    "member_id": "9771240",
    "name": "윤창현"
  }, {
    "member_id": "9770876",
    "name": "윤호중"
  }, {
    "member_id": "9770813",
    "name": "윤후덕"
  }, {
    "member_id": "9770905",
    "name": "이개호"
  }, {
    "member_id": "9771191",
    "name": "이규민"
  }, {
    "member_id": "9771260",
    "name": "이동주"
  }, {
    "member_id": "9771151",
    "name": "이성만"
  }, {
    "member_id": "9771269",
    "name": "이수진"
  }, {
    "member_id": "9771158",
    "name": "이용빈"
  }, {
    "member_id": "9771115",
    "name": "이용선"
  }, {
    "member_id": "9771184",
    "name": "이용우"
  }, {
    "member_id": "9771213",
    "name": "이원택"
  }, {
    "member_id": "9771060",
    "name": "이재정"
  }, {
    "member_id": "9771205",
    "name": "이정문"
  }, {
    "member_id": "9771242",
    "name": "이종성"
  }, {
    "member_id": "9771138",
    "name": "이주환"
  }, {
    "member_id": "9770835",
    "name": "이채익"
  }, {
    "member_id": "9771002",
    "name": "이철규"
  }, {
    "member_id": "9771190",
    "name": "이탄희"
  }, {
    "member_id": "9771129",
    "name": "이해식"
  }, {
    "member_id": "9771157",
    "name": "이형석"
  }, {
    "member_id": "9770839",
    "name": "인재근"
  }, {
    "member_id": "9771177",
    "name": "임오경"
  }, {
    "member_id": "9771000",
    "name": "임종성"
  }, {
    "member_id": "9771203",
    "name": "임호선"
  }, {
    "member_id": "9771110",
    "name": "장경태"
  }, {
    "member_id": "9771160",
    "name": "장철민"
  }, {
    "member_id": "9771275",
    "name": "장혜영"
  }, {
    "member_id": "9771139",
    "name": "전봉민"
  }, {
    "member_id": "9771272",
    "name": "전용기"
  }, {
    "member_id": "9770951",
    "name": "전재수"
  }, {
    "member_id": "9771140",
    "name": "정동만"
  }, {
    "member_id": "9771200",
    "name": "정정순"
  }, {
    "member_id": "9771006",
    "name": "정진석"
  }, {
    "member_id": "9771189",
    "name": "정찬민"
  }, {
    "member_id": "9771114",
    "name": "정청래"
  }, {
    "member_id": "9771068",
    "name": "정춘숙"
  }, {
    "member_id": "9771122",
    "name": "정태호"
  }, {
    "member_id": "9771264",
    "name": "정필모"
  }, {
    "member_id": "9771229",
    "name": "정희용"
  }, {
    "member_id": "9770450",
    "name": "조경태"
  }, {
    "member_id": "9771247",
    "name": "조명희"
  }, {
    "member_id": "9770973",
    "name": "조승래"
  }, {
    "member_id": "9771156",
    "name": "조오섭"
  }, {
    "member_id": "9770990",
    "name": "조응천"
  }, {
    "member_id": "9771244",
    "name": "조태용"
  }, {
    "member_id": "9771215",
    "name": "주철현"
  }, {
    "member_id": "9771250",
    "name": "지성호"
  }, {
    "member_id": "9770852",
    "name": "진선미"
  }, {
    "member_id": "9771117",
    "name": "진성준"
  }, {
    "member_id": "9771112",
    "name": "천준호"
  }, {
    "member_id": "9771119",
    "name": "최기상"
  }, {
    "member_id": "9771188",
    "name": "최종윤"
  }, {
    "member_id": "9771194",
    "name": "최춘식"
  }, {
    "member_id": "9771231",
    "name": "최형두"
  }, {
    "member_id": "9771267",
    "name": "최혜영"
  }, {
    "member_id": "9771234",
    "name": "하영제"
  }, {
    "member_id": "9771211",
    "name": "한병도"
  }, {
    "member_id": "9771182",
    "name": "한준호"
  }, {
    "member_id": "9771196",
    "name": "허영"
  }, {
    "member_id": "9771256",
    "name": "허은아"
  }, {
    "member_id": "9771149",
    "name": "허종식"
  }, {
    "member_id": "9771146",
    "name": "홍석준"
  }, {
    "member_id": "9771167",
    "name": "홍성국"
  }, {
    "member_id": "9770864",
    "name": "홍익표"
  }, {
    "member_id": "9771183",
    "name": "홍정민"
  }, {
    "member_id": "9771161",
    "name": "황운하"
  }],
  "members_oppose": [{
    "member_id": "9771126",
    "name": "유경준"
  }, {
    "member_id": "9770812",
    "name": "윤재옥"
  }, {
    "member_id": "9770914",
    "name": "이종배"
  }],
  "members_abstain": [{
    "member_id": "9770679",
    "name": "권성동"
  }, {
    "member_id": "9771136",
    "name": "김미애"
  }, {
    "member_id": "9771144",
    "name": "김승수"
  }, {
    "member_id": "9771127",
    "name": "김웅"
  }, {
    "member_id": "9771023",
    "name": "김정재"
  }, {
    "member_id": "9771125",
    "name": "박진"
  }, {
    "member_id": "9770996",
    "name": "송석준"
  }, {
    "member_id": "9771287",
    "name": "양이원영"
  }, {
    "member_id": "9771028",
    "name": "이만희"
  }, {
    "member_id": "9771251",
    "name": "이영"
  }, {
    "member_id": "9770837",
    "name": "이헌승"
  }, {
    "member_id": "9771041",
    "name": "임이자"
  }, {
    "member_id": "9771253",
    "name": "전주혜"
  }, {
    "member_id": "9771245",
    "name": "정경희"
  }, {
    "member_id": "9771103",
    "name": "정점식"
  }, {
    "member_id": "9770883",
    "name": "주호영"
  }, {
    "member_id": "9771252",
    "name": "최승재"
  }, {
    "member_id": "9771286",
    "name": "태영호"
  }, {
    "member_id": "9771197",
    "name": "한기호"
  }],
  "result": "수정가결",
  "kind": "법률안",
  "committee": "국토교통위원회"
}