{
  "bill_id": "PRC_X1C7O1I1S1F5K1O2J4U3W0H8U1A8H4",
  "bill_no": "2010170",
  "id_master": 150320,
  "session": 20,
  "name": "지속가능한 기반시설 관리 기본법안",
  "summary": "제안이유\n\n  1970년대를 전후하여 우리경제가 압축성장기에 진입하면서 본격적으로 건설하기 시작한 국가 주요 기반시설의 노후화가 진전되면서 본래 기능을 발휘하는데 한계를 드러내고 있을 뿐만 아니라 안전사고의 우려도 커지고 있으므로 이에 대한 체계적인 유지관리의 필요성이 증대되고 있음.\n  한편, 지난 1990년대 중반에 발생한 성수대교 및 삼풍백화점 붕괴사고 이후 「시설물의 안전관리에 관한 특별법」이 제정되면서 중대형시설물에 대한 주기적인 안전점검을 통해 중대결함을 사전에 발견하고 보수보강을 의무화하는 등 구조적 안전성 측면에서는 잘 대처하고 있는 것으로 평가할 수 있으나, 시설물의 노후화에 대비한 선제적인 유지관리 및 안전점검 이후 체계적인 보수ㆍ보강을 위한 이행력 확보 등 시설물 생애주기비용을 절감하면서 성능을 최대화할 수 있는 선진적인 시설물 유지관리를 위한 틀이 아직 마련되어 있지 않은 것이 현실임.\n  이에 우리나라보다 먼저 시설물 유지관리에 대한 문제를 경험한 미국과 일본 등 선진국의 사례를 살펴보면, 이들은 기반시설 노후화에 적절하게 대응하지 못할 경우 안전문제뿐만 아니라 관리비용의 급격한 증가라는 더 큰 사회적 문제를 야기함을 깨닫고 기반시설 유지관리의 방식을 사후적 대응에서 선제적 투자로 전환함과 아울러 센서, 로봇 검사 등 유지관리 기법의 효율화를 위한 기술개발을 적극적으로 추진한 것을 알 수 있음.\n  이와 같은 선진국의 사례를 토대로 노후화 되어 가고 있는 공공기반시설에 대해 전략적 투자와 관리방식을 도입함으로써 안전사고를 미연에 방지하고 기존시설의 수명연장과 성능개선을 통해 재정투자의 효율성을 제고하면서, 낙후된 유지관리 관련 산업을 고부가가치화하고 새로운 일자리를 창출하기 위한 노력을 기울일 시기가 도래하였다고 봄.\n  이를 위해 국토교통부장관이 기반시설의 체계적인 유지관리를 위해 5년 주기로 기본계획을 수립？시행하도록 하고, 기본계획에 따라 관리감독기관이 5년 주기의 관리계획을 수립ㆍ시행하도록 하면서, 국무총리를 위원장으로 하는 ‘기반시설관리위원회’를 두어 최소유지관리기준과 성능개선기준을 설정하고 이와 함께 정부의 지원 원칙을 정하고 관리주체의 성능개선 충당금 적립을 의무화함으로써 국민이 보다 안전하고 편리하게 기반시설을 활용하도록 하고, 나아가 국가경제 발전에 기여하려는 것임.\n\n\n주요내용\n\n가. 국토교통부장관은 기반시설의 체계적인 유지관리를 위하여 기반시설 관리에 관한 기본계획을 5년마다 수립하도록 하고, 기본계획 수립 시에는 기반시설관리위원회와 국무회의의 심의를 거치도록 함(안 제8조).\n나. 관리감독기관의 장은 기본계획에 따라 소관 기반시설에 대한 관리계획을 5년마다 수립하여 국토교통부장관에게 제출하도록 하고, 기반시설관리위원회에서 내용을 심의하여 관리감독기관의 장에게 그 결과를 통보함(안 제9조).\n다. 관계 중앙행정기관의 장은 소관 기반시설의 유형별로 최소유지관리기준을 설정하여 고시하여야 함(안 제11조).\n라. 관리주체는 소관 기반시설 중 대통령령으로 정하는 시설에 대하여 구조적 안전성, 내구성, 사용성 등을 종합적으로 평가하는 성능평가를 실시하여야 함(안 제12조).\n마. 관계 중앙행정기관의 장은 소관 기반시설의 유형별로 관리주체가 유지관리보다 성능개선이 유리한지에 대해 판단할 수 있도록 성능개선기준을 설정？고시할 수 있음(안 제13조).\n바. 관계 중앙행정기관의 장, 시？도지사 및 관리주체는 기반시설의 유지관리현황, 최소유지관리기준의 충족 여부, 성능개선의 타당성 등을 파악하기 위하여 실태조사를 실시할 수 있음(안 제14조).\n사. 기반시설관리위원회는 관계 중앙행정기관의 장 및 시？도지사의 의견을 받아 유지관리 우수 기반시설을 선정할 수 있으며, 국가의 재정지원 비율의 상향 등 인센티브를 부여하도록 함(안 제15조).\n아. 국무총리 소속의 기반시설관리위원회를 두어 기본계획ㆍ관리계획, 최소유지관리기준 및 성능개선기준의 설정 등을 심의하고, 위원회의 업무를 지원하기 위하여 국토교통부장관 소속으로 기반시설관리기획단을 둠(안 제18조).\n자. 관리주체가 유지관리비용을 지원받으려면 관리계획을 수립하여야 하고, 성능개선비용을 지원받기 위해서는 관리계획을 수립하고 성능개선 충당금을 적립하여야 함(안 제21조).\n차. 국가 및 지방자치단체는 기반시설의 체계적인 유지관리 및 성능개선을 위해 관리주체에 대하여 조사ㆍ진단, 보수ㆍ보강, 성능개선 비용 등을 보조ㆍ융자할 수 있도록 함(안 제22조).\n카. 사용료를 부과하는 관리주체는 기반시설의 사용자에게 유지관리 및 성능개선에 필요한 재원 조성을 위한 부담금을 부과？징수할 수 있으며, 사용료의 10퍼센트 범위에서 부과하되 구체적인 기준 등은 해당 기반시설 관계 법령에서 정하도록 함(안 제23조).\n타. 관리주체가 기반시설의 노후화에 대비하여 적립하는 성능개선 충당금은 관리？운영 수익금, 일반회계 및 교통시설특별회계로부터의 전입금, 공공기관 운영 효율화를 통한 자금 등을 재원으로 함(안 제24조).",
  "related_bill_ids": [],
  "proposal_date": "2017-11-15",
  "vote_date": "2018-12-07",
  "members_voting": 204,
  "members_registered": 299,
  "total_votes": 204,
  "total_agree": 195,
  "total_oppose": 0,
  "total_abstain": 9,
  "members_agree": [{
    "member_id": "9770933",
    "name": "강병원"
  }, {
    "member_id": "9771036",
    "name": "강석진"
  }, {
    "member_id": "9770512",
    "name": "강석호"
  }, {
    "member_id": "9771054",
    "name": "강효상"
  }, {
    "member_id": "9770708",
    "name": "경대수"
  }, {
    "member_id": "9770931",
    "name": "고용진"
  }, {
    "member_id": "9770956",
    "name": "곽상도"
  }, {
    "member_id": "9771066",
    "name": "권미혁"
  }, {
    "member_id": "9770679",
    "name": "권성동"
  }, {
    "member_id": "9770937",
    "name": "금태섭"
  }, {
    "member_id": "9770927",
    "name": "기동민"
  }, {
    "member_id": "9770712",
    "name": "김경협"
  }, {
    "member_id": "9770523",
    "name": "김광림"
  }, {
    "member_id": "9771044",
    "name": "김규환"
  }, {
    "member_id": "9770716",
    "name": "김기선"
  }, {
    "member_id": "9770719",
    "name": "김도읍"
  }, {
    "member_id": "9770721",
    "name": "김명연"
  }, {
    "member_id": "9770895",
    "name": "김무성"
  }, {
    "member_id": "9770723",
    "name": "김민기"
  }, {
    "member_id": "9770983",
    "name": "김병관"
  }, {
    "member_id": "9770941",
    "name": "김병기"
  }, {
    "member_id": "9770984",
    "name": "김병욱"
  }, {
    "member_id": "9770527",
    "name": "김상희"
  }, {
    "member_id": "9770930",
    "name": "김선동"
  }, {
    "member_id": "9771065",
    "name": "김성수"
  }, {
    "member_id": "9770985",
    "name": "김성원"
  }, {
    "member_id": "9770727",
    "name": "김성찬"
  }, {
    "member_id": "9771046",
    "name": "金成泰"
  }, {
    "member_id": "9771089",
    "name": "김성환"
  }, {
    "member_id": "9770534",
    "name": "김세연"
  }, {
    "member_id": "9771053",
    "name": "김순례"
  }, {
    "member_id": "9771049",
    "name": "김승희"
  }, {
    "member_id": "9770538",
    "name": "김영우"
  }, {
    "member_id": "9770975",
    "name": "김영주"
  }, {
    "member_id": "9770981",
    "name": "김영진"
  }, {
    "member_id": "9770934",
    "name": "김영호"
  }, {
    "member_id": "9770310",
    "name": "김재경"
  }, {
    "member_id": "9771087",
    "name": "김재원"
  }, {
    "member_id": "9770993",
    "name": "김정우"
  }, {
    "member_id": "9771023",
    "name": "김정재"
  }, {
    "member_id": "9771090",
    "name": "김정호"
  }, {
    "member_id": "9770316",
    "name": "김정훈"
  }, {
    "member_id": "9770978",
    "name": "김종훈"
  }, {
    "member_id": "9770740",
    "name": "김진태"
  }, {
    "member_id": "9770982",
    "name": "김진표"
  }, {
    "member_id": "9770986",
    "name": "김철민"
  }, {
    "member_id": "9770742",
    "name": "김태흠"
  }, {
    "member_id": "9770670",
    "name": "김학용"
  }, {
    "member_id": "9770744",
    "name": "김한표"
  }, {
    "member_id": "9770953",
    "name": "김해영"
  }, {
    "member_id": "9771061",
    "name": "김현권"
  }, {
    "member_id": "9771055",
    "name": "김현아"
  }, {
    "member_id": "9770903",
    "name": "나경원"
  }, {
    "member_id": "9770752",
    "name": "남인순"
  }, {
    "member_id": "9770753",
    "name": "노웅래"
  }, {
    "member_id": "9771091",
    "name": "맹성규"
  }, {
    "member_id": "9771042",
    "name": "문진국"
  }, {
    "member_id": "9770964",
    "name": "민경욱"
  }, {
    "member_id": "9770761",
    "name": "민병두"
  }, {
    "member_id": "9770764",
    "name": "민홍철"
  }, {
    "member_id": "9771056",
    "name": "박경미"
  }, {
    "member_id": "9770911",
    "name": "박광온"
  }, {
    "member_id": "9770768",
    "name": "박덕흠"
  }, {
    "member_id": "9770770",
    "name": "박범계"
  }, {
    "member_id": "9770090",
    "name": "박병석"
  }, {
    "member_id": "9770944",
    "name": "박성중"
  }, {
    "member_id": "9770347",
    "name": "박영선"
  }, {
    "member_id": "9771030",
    "name": "박완수"
  }, {
    "member_id": "9770774",
    "name": "박완주"
  }, {
    "member_id": "9770929",
    "name": "박용진"
  }, {
    "member_id": "9770776",
    "name": "박인숙"
  }, {
    "member_id": "9770950",
    "name": "박재호"
  }, {
    "member_id": "9770995",
    "name": "박정"
  }, {
    "member_id": "9770932",
    "name": "박주민"
  }, {
    "member_id": "9770963",
    "name": "박찬대"
  }, {
    "member_id": "9770779",
    "name": "박홍근"
  }, {
    "member_id": "9771025",
    "name": "백승주"
  }, {
    "member_id": "9770573",
    "name": "백재현"
  }, {
    "member_id": "9770980",
    "name": "백혜련"
  }, {
    "member_id": "9771092",
    "name": "서삼석"
  }, {
    "member_id": "9770784",
    "name": "서영교"
  }, {
    "member_id": "9770898",
    "name": "서청원"
  }, {
    "member_id": "9771035",
    "name": "서형수"
  }, {
    "member_id": "9770786",
    "name": "설훈"
  }, {
    "member_id": "9771008",
    "name": "성일종"
  }, {
    "member_id": "9770999",
    "name": "소병훈"
  }, {
    "member_id": "9771019",
    "name": "손금주"
  }, {
    "member_id": "9770935",
    "name": "손혜원"
  }, {
    "member_id": "9771093",
    "name": "송갑석"
  }, {
    "member_id": "9771001",
    "name": "송기헌"
  }, {
    "member_id": "9770996",
    "name": "송석준"
  }, {
    "member_id": "9771094",
    "name": "송언석"
  }, {
    "member_id": "9770967",
    "name": "송영길"
  }, {
    "member_id": "9771058",
    "name": "송옥주"
  }, {
    "member_id": "9771039",
    "name": "송희경"
  }, {
    "member_id": "9770792",
    "name": "신경민"
  }, {
    "member_id": "9770968",
    "name": "신동근"
  }, {
    "member_id": "9771045",
    "name": "신보라"
  }, {
    "member_id": "9770921",
    "name": "신상진"
  }, {
    "member_id": "9770989",
    "name": "신창현"
  }, {
    "member_id": "9771086",
    "name": "심기준"
  }, {
    "member_id": "9770798",
    "name": "심재권"
  }, {
    "member_id": "9770138",
    "name": "심재철"
  }, {
    "member_id": "9770587",
    "name": "안규백"
  }, {
    "member_id": "9770372",
    "name": "안민석"
  }, {
    "member_id": "9770919",
    "name": "안상수"
  }, {
    "member_id": "9771017",
    "name": "안호영"
  }, {
    "member_id": "9771010",
    "name": "어기구"
  }, {
    "member_id": "9771034",
    "name": "엄용수"
  }, {
    "member_id": "9770591",
    "name": "여상규"
  }, {
    "member_id": "9770802",
    "name": "염동열"
  }, {
    "member_id": "9771037",
    "name": "오영훈"
  }, {
    "member_id": "9770380",
    "name": "오제세"
  }, {
    "member_id": "9770871",
    "name": "우상호"
  }, {
    "member_id": "9770872",
    "name": "우원식"
  }, {
    "member_id": "9770592",
    "name": "원유철"
  }, {
    "member_id": "9770386",
    "name": "원혜영"
  }, {
    "member_id": "9771038",
    "name": "위성곤"
  }, {
    "member_id": "9770387",
    "name": "유기준"
  }, {
    "member_id": "9771050",
    "name": "유민봉"
  }, {
    "member_id": "9770874",
    "name": "유승희"
  }, {
    "member_id": "9770596",
    "name": "유재중"
  }, {
    "member_id": "9770808",
    "name": "윤관석"
  }, {
    "member_id": "9770955",
    "name": "윤상직"
  }, {
    "member_id": "9770598",
    "name": "윤상현"
  }, {
    "member_id": "9770812",
    "name": "윤재옥"
  }, {
    "member_id": "9771096",
    "name": "윤준호"
  }, {
    "member_id": "9771032",
    "name": "윤한홍"
  }, {
    "member_id": "9770813",
    "name": "윤후덕"
  }, {
    "member_id": "9771097",
    "name": "이규희"
  }, {
    "member_id": "9771028",
    "name": "이만희"
  }, {
    "member_id": "9770602",
    "name": "이명수"
  }, {
    "member_id": "9771072",
    "name": "이상돈"
  }, {
    "member_id": "9770414",
    "name": "이상민"
  }, {
    "member_id": "9771098",
    "name": "이상헌"
  }, {
    "member_id": "9770416",
    "name": "이석현"
  }, {
    "member_id": "9771088",
    "name": "이수혁"
  }, {
    "member_id": "9770826",
    "name": "이원욱"
  }, {
    "member_id": "9770878",
    "name": "이인영"
  }, {
    "member_id": "9770829",
    "name": "이장우"
  }, {
    "member_id": "9771060",
    "name": "이재정"
  }, {
    "member_id": "9770916",
    "name": "이정현"
  }, {
    "member_id": "9770194",
    "name": "이종걸"
  }, {
    "member_id": "9770945",
    "name": "이종구"
  }, {
    "member_id": "9770914",
    "name": "이종배"
  }, {
    "member_id": "9770621",
    "name": "이진복"
  }, {
    "member_id": "9770835",
    "name": "이채익"
  }, {
    "member_id": "9771002",
    "name": "이철규"
  }, {
    "member_id": "9771063",
    "name": "이철희"
  }, {
    "member_id": "9770623",
    "name": "이춘석"
  }, {
    "member_id": "9770836",
    "name": "이학영"
  }, {
    "member_id": "9770837",
    "name": "이헌승"
  }, {
    "member_id": "9770838",
    "name": "이현재"
  }, {
    "member_id": "9771099",
    "name": "이후삼"
  }, {
    "member_id": "9770939",
    "name": "이훈"
  }, {
    "member_id": "9770839",
    "name": "인재근"
  }, {
    "member_id": "9771041",
    "name": "임이자"
  }, {
    "member_id": "9771000",
    "name": "임종성"
  }, {
    "member_id": "9771026",
    "name": "장석춘"
  }, {
    "member_id": "9770951",
    "name": "전재수"
  }, {
    "member_id": "9770846",
    "name": "전해철"
  }, {
    "member_id": "9770946",
    "name": "전현희"
  }, {
    "member_id": "9770926",
    "name": "전혜숙"
  }, {
    "member_id": "9770439",
    "name": "정갑윤"
  }, {
    "member_id": "9770881",
    "name": "정성호"
  }, {
    "member_id": "9770230",
    "name": "정세균"
  }, {
    "member_id": "9770928",
    "name": "정양석"
  }, {
    "member_id": "9770907",
    "name": "정용기"
  }, {
    "member_id": "9770965",
    "name": "정유섭"
  }, {
    "member_id": "9771006",
    "name": "정진석"
  }, {
    "member_id": "9771068",
    "name": "정춘숙"
  }, {
    "member_id": "9770958",
    "name": "정태옥"
  }, {
    "member_id": "9771064",
    "name": "제윤경"
  }, {
    "member_id": "9770450",
    "name": "조경태"
  }, {
    "member_id": "9770973",
    "name": "조승래"
  }, {
    "member_id": "9770990",
    "name": "조응천"
  }, {
    "member_id": "9770456",
    "name": "조정식"
  }, {
    "member_id": "9771052",
    "name": "조훈현"
  }, {
    "member_id": "9770992",
    "name": "주광덕"
  }, {
    "member_id": "9770462",
    "name": "진영"
  }, {
    "member_id": "9771027",
    "name": "최교일"
  }, {
    "member_id": "9771043",
    "name": "최연혜"
  }, {
    "member_id": "9771059",
    "name": "최운열"
  }, {
    "member_id": "9770952",
    "name": "최인호"
  }, {
    "member_id": "9771100",
    "name": "최재성"
  }, {
    "member_id": "9770962",
    "name": "추경호"
  }, {
    "member_id": "9770994",
    "name": "표창원"
  }, {
    "member_id": "9770477",
    "name": "한선교"
  }, {
    "member_id": "9770859",
    "name": "한정애"
  }, {
    "member_id": "9770860",
    "name": "함진규"
  }, {
    "member_id": "9770676",
    "name": "홍영표"
  }, {
    "member_id": "9770864",
    "name": "홍익표"
  }, {
    "member_id": "9770913",
    "name": "홍철호"
  }, {
    "member_id": "9770669",
    "name": "황영철"
  }, {
    "member_id": "9770936",
    "name": "황희"
  }],
  "members_oppose": [],
  "members_abstain": [{
    "member_id": "9770961",
    "name": "곽대훈"
  }, {
    "member_id": "9770998",
    "name": "권칠승"
  }, {
    "member_id": "9770997",
    "name": "김두관"
  }, {
    "member_id": "9771024",
    "name": "김석기"
  }, {
    "member_id": "9770908",
    "name": "박맹우"
  }, {
    "member_id": "9771051",
    "name": "윤종필"
  }, {
    "member_id": "9771040",
    "name": "이종명"
  }, {
    "member_id": "9770499",
    "name": "이주영"
  }, {
    "member_id": "9770659",
    "name": "추미애"
  }],
  "result": "수정가결",
  "kind": "법률안",
  "committee": "국토교통위원회"
}