{
  "bill_id": "PRC_G1T8K1B1H2P7Q1O3L3S5A5K3L8C8E4",
  "bill_no": "2017728",
  "id_master": 152143,
  "session": 20,
  "name": "신용협동조합법 일부개정법률안(대안)",
  "summary": "대안의 제안이유 \n 국민생활 및 기업활동과 밀접하게 관련되어 있는 인가 및 신고 민원의 처리절차를 법령에서 명확하게 규정함으로써 관련 민원의 투명하고 신속한 처리와 일선 행정기관의 적극행정을 유도하려는 것임.\n 또한, 조합 및 중앙회의 임원 선거 관리를 선거관리위원회에 위탁할 수 있는 법률적 근거를 마련함으로써 공정한 선거를 통해 신용협동조합의 임원이 선출되도록 하려는 것임.\n 그리고, 신용협동조합의 예금자보호기금에 대하여 정부로부터 자금을 차입할 근거를 마련하고 목표기금제를 도입하는 등 타 예금보호법령과 비교하여 일부 미진한 부분을 보완하여, 신용협동조합 예금자보호제도의 건전성과 신뢰성을 확보하고 전체 예금자보호제도의 통일성을 기하고자 함.\n\n대안의 주요내용\n가. 신용협동조합설립 인가의 신청을 받거나 공제규정 인가사항의 변경신고를 받은 경우 법령 등에서 정한 기간 내에 인가 또는 신고수리 여부를 신청인에게 통지하도록 하고, 그 기간 내에 인가 또는 신고수리 여부나 처리기간의 연장을 통지하지 아니한 경우에는 인가 또는 신고수리를 한 것으로 간주(看做)하는 제도를 도입함(안 제8조제3항 및 제97조제4항·제5항 신설).\n나. 조합 및 중앙회의 임원 선거 관리를 선거관리위원회에 위탁할 수 있는 법률적 근거를 마련함(안 제27조의3 신설, 안 제72조제8항).\n다. 타 상호금융기관과 동일하게 조합 간 합병한 이후 등기부 등 공부에 표시된 소멸된 조합의 명의를 존속하거나 설립된 조합의 명의로 간주하여, 변경등기에 소요되는 등기비용, 인력, 시간의 절감을 통해 존속조합 등의 건전성을 제고하고 업무부담을 경감하도록 함(안 제55조제4항 신설).\n라. 조합 등이 예탁금 등을 조합원 등에게 지급할 수 없는 경우에 중앙회에 대한 변제금청구권의 소멸시효를 타 예금보호기관과 동일하게 5년으로 하고, 변제금청구권의 행사를 촉구하기 위하여 예금자 등에게 안내·통지 등을 하더라도 시효중단의 효력이 없는 것으로 하여, 금융권 공통으로 적용되는 예금자보호제도의 통일성 및 안전성을 확보하도록 함(안 제80조의2제6항 및 제7항 신설).\n마. 타 예금보호기관과 동일하게 정부, 한국은행 및 금융기관에서 자금을 차입할 수 있게 하여, 급격한 금융위기상황을 대비함으로써 예금자보호기금의 안정성을 제고하고 신뢰성을 확보하고자 함(안 제80조의3제1항제3호).\n바. 신용협동조합 예금자보호기금 기금적립액의 목표규모를 정하고 동 기금의 적립액이 목표규모에 도달하면 신용협동조합이 납부하는 출연금을 감면하도록 함(안 제80조의7 신설).\n사. 조합이 파산하는 경우에 타 상호금융기관과 동일하게 중앙회장이 임직원을 파산관재인으로 추천할 수 있게 하여, 원할하게 파산절차를 진행하고 기금회수에 만전을 기할 수 있게 함(안 제88조의2).",
  "related_bill_ids": ["ARC_S1K7W0D8R2N8M1F7Y2U3M4S7V8N7M7", "PRC_D1O7S1M1L1P3Y1O6O4L4H3C9J6I5Y6", "PRC_A1P7C1A2B2G8M1P6N4M2W3R7K5C0C8"],
  "proposal_date": "2018-12-26",
  "vote_date": "2018-12-27",
  "members_voting": 178,
  "members_registered": 298,
  "total_votes": 178,
  "total_agree": 171,
  "total_oppose": 0,
  "total_abstain": 7,
  "members_agree": [{
    "member_id": "9770276",
    "name": "강길부"
  }, {
    "member_id": "9770933",
    "name": "강병원"
  }, {
    "member_id": "9771036",
    "name": "강석진"
  }, {
    "member_id": "9770279",
    "name": "강창일"
  }, {
    "member_id": "9771007",
    "name": "강훈식"
  }, {
    "member_id": "9770708",
    "name": "경대수"
  }, {
    "member_id": "9771066",
    "name": "권미혁"
  }, {
    "member_id": "9770977",
    "name": "권은희"
  }, {
    "member_id": "9770998",
    "name": "권칠승"
  }, {
    "member_id": "9770937",
    "name": "금태섭"
  }, {
    "member_id": "9770927",
    "name": "기동민"
  }, {
    "member_id": "9770713",
    "name": "김관영"
  }, {
    "member_id": "9770523",
    "name": "김광림"
  }, {
    "member_id": "9771011",
    "name": "김광수"
  }, {
    "member_id": "9770719",
    "name": "김도읍"
  }, {
    "member_id": "9770997",
    "name": "김두관"
  }, {
    "member_id": "9770721",
    "name": "김명연"
  }, {
    "member_id": "9770723",
    "name": "김민기"
  }, {
    "member_id": "9770983",
    "name": "김병관"
  }, {
    "member_id": "9770984",
    "name": "김병욱"
  }, {
    "member_id": "9771077",
    "name": "김삼화"
  }, {
    "member_id": "9770725",
    "name": "김상훈"
  }, {
    "member_id": "9771024",
    "name": "김석기"
  }, {
    "member_id": "9770942",
    "name": "김성식"
  }, {
    "member_id": "9770985",
    "name": "김성원"
  }, {
    "member_id": "9770727",
    "name": "김성찬"
  }, {
    "member_id": "9771089",
    "name": "김성환"
  }, {
    "member_id": "9770534",
    "name": "김세연"
  }, {
    "member_id": "9770538",
    "name": "김영우"
  }, {
    "member_id": "9770981",
    "name": "김영진"
  }, {
    "member_id": "9770934",
    "name": "김영호"
  }, {
    "member_id": "9771087",
    "name": "김재원"
  }, {
    "member_id": "9770993",
    "name": "김정우"
  }, {
    "member_id": "9771083",
    "name": "김종대"
  }, {
    "member_id": "9771009",
    "name": "김종민"
  }, {
    "member_id": "9771016",
    "name": "김종회"
  }, {
    "member_id": "9770986",
    "name": "김철민"
  }, {
    "member_id": "9770741",
    "name": "김태년"
  }, {
    "member_id": "9770670",
    "name": "김학용"
  }, {
    "member_id": "9770991",
    "name": "김한정"
  }, {
    "member_id": "9770744",
    "name": "김한표"
  }, {
    "member_id": "9770953",
    "name": "김해영"
  }, {
    "member_id": "9771061",
    "name": "김현권"
  }, {
    "member_id": "9771055",
    "name": "김현아"
  }, {
    "member_id": "9770752",
    "name": "남인순"
  }, {
    "member_id": "9770753",
    "name": "노웅래"
  }, {
    "member_id": "9771091",
    "name": "맹성규"
  }, {
    "member_id": "9771042",
    "name": "문진국"
  }, {
    "member_id": "9770084",
    "name": "문희상"
  }, {
    "member_id": "9770964",
    "name": "민경욱"
  }, {
    "member_id": "9770761",
    "name": "민병두"
  }, {
    "member_id": "9770764",
    "name": "민홍철"
  }, {
    "member_id": "9770768",
    "name": "박덕흠"
  }, {
    "member_id": "9771073",
    "name": "박선숙"
  }, {
    "member_id": "9770944",
    "name": "박성중"
  }, {
    "member_id": "9770987",
    "name": "박순자"
  }, {
    "member_id": "9770774",
    "name": "박완주"
  }, {
    "member_id": "9770776",
    "name": "박인숙"
  }, {
    "member_id": "9770950",
    "name": "박재호"
  }, {
    "member_id": "9770995",
    "name": "박정"
  }, {
    "member_id": "9770566",
    "name": "박주선"
  }, {
    "member_id": "9770568",
    "name": "박지원"
  }, {
    "member_id": "9770963",
    "name": "박찬대"
  }, {
    "member_id": "9770779",
    "name": "박홍근"
  }, {
    "member_id": "9770980",
    "name": "백혜련"
  }, {
    "member_id": "9770356",
    "name": "변재일"
  }, {
    "member_id": "9771092",
    "name": "서삼석"
  }, {
    "member_id": "9770898",
    "name": "서청원"
  }, {
    "member_id": "9771035",
    "name": "서형수"
  }, {
    "member_id": "9770999",
    "name": "소병훈"
  }, {
    "member_id": "9770935",
    "name": "손혜원"
  }, {
    "member_id": "9771001",
    "name": "송기헌"
  }, {
    "member_id": "9770996",
    "name": "송석준"
  }, {
    "member_id": "9771094",
    "name": "송언석"
  }, {
    "member_id": "9771058",
    "name": "송옥주"
  }, {
    "member_id": "9771039",
    "name": "송희경"
  }, {
    "member_id": "9770968",
    "name": "신동근"
  }, {
    "member_id": "9771069",
    "name": "신용현"
  }, {
    "member_id": "9770989",
    "name": "신창현"
  }, {
    "member_id": "9771086",
    "name": "심기준"
  }, {
    "member_id": "9770869",
    "name": "심상정"
  }, {
    "member_id": "9770798",
    "name": "심재권"
  }, {
    "member_id": "9770138",
    "name": "심재철"
  }, {
    "member_id": "9770372",
    "name": "안민석"
  }, {
    "member_id": "9770919",
    "name": "안상수"
  }, {
    "member_id": "9771017",
    "name": "안호영"
  }, {
    "member_id": "9771010",
    "name": "어기구"
  }, {
    "member_id": "9771034",
    "name": "엄용수"
  }, {
    "member_id": "9770802",
    "name": "염동열"
  }, {
    "member_id": "9770918",
    "name": "오신환"
  }, {
    "member_id": "9771037",
    "name": "오영훈"
  }, {
    "member_id": "9770380",
    "name": "오제세"
  }, {
    "member_id": "9770871",
    "name": "우상호"
  }, {
    "member_id": "9770872",
    "name": "우원식"
  }, {
    "member_id": "9771038",
    "name": "위성곤"
  }, {
    "member_id": "9770966",
    "name": "유동수"
  }, {
    "member_id": "9771050",
    "name": "유민봉"
  }, {
    "member_id": "9770874",
    "name": "유승희"
  }, {
    "member_id": "9770912",
    "name": "유의동"
  }, {
    "member_id": "9770808",
    "name": "윤관석"
  }, {
    "member_id": "9770955",
    "name": "윤상직"
  }, {
    "member_id": "9770598",
    "name": "윤상현"
  }, {
    "member_id": "9771085",
    "name": "윤소하"
  }, {
    "member_id": "9771095",
    "name": "윤일규"
  }, {
    "member_id": "9771051",
    "name": "윤종필"
  }, {
    "member_id": "9770876",
    "name": "윤호중"
  }, {
    "member_id": "9770813",
    "name": "윤후덕"
  }, {
    "member_id": "9771097",
    "name": "이규희"
  }, {
    "member_id": "9771080",
    "name": "이동섭"
  }, {
    "member_id": "9771028",
    "name": "이만희"
  }, {
    "member_id": "9770602",
    "name": "이명수"
  }, {
    "member_id": "9771072",
    "name": "이상돈"
  }, {
    "member_id": "9770414",
    "name": "이상민"
  }, {
    "member_id": "9771098",
    "name": "이상헌"
  }, {
    "member_id": "9770416",
    "name": "이석현"
  }, {
    "member_id": "9771088",
    "name": "이수혁"
  }, {
    "member_id": "9771067",
    "name": "이용득"
  }, {
    "member_id": "9770829",
    "name": "이장우"
  }, {
    "member_id": "9771060",
    "name": "이재정"
  }, {
    "member_id": "9771082",
    "name": "이정미"
  }, {
    "member_id": "9770916",
    "name": "이정현"
  }, {
    "member_id": "9770945",
    "name": "이종구"
  }, {
    "member_id": "9770914",
    "name": "이종배"
  }, {
    "member_id": "9770621",
    "name": "이진복"
  }, {
    "member_id": "9771063",
    "name": "이철희"
  }, {
    "member_id": "9770623",
    "name": "이춘석"
  }, {
    "member_id": "9771076",
    "name": "이태규"
  }, {
    "member_id": "9770836",
    "name": "이학영"
  }, {
    "member_id": "9770625",
    "name": "이학재"
  }, {
    "member_id": "9770838",
    "name": "이현재"
  }, {
    "member_id": "9771099",
    "name": "이후삼"
  }, {
    "member_id": "9770939",
    "name": "이훈"
  }, {
    "member_id": "9770839",
    "name": "인재근"
  }, {
    "member_id": "9771041",
    "name": "임이자"
  }, {
    "member_id": "9771000",
    "name": "임종성"
  }, {
    "member_id": "9770688",
    "name": "장병완"
  }, {
    "member_id": "9771079",
    "name": "장정숙"
  }, {
    "member_id": "9770951",
    "name": "전재수"
  }, {
    "member_id": "9770946",
    "name": "전현희"
  }, {
    "member_id": "9770926",
    "name": "전혜숙"
  }, {
    "member_id": "9770439",
    "name": "정갑윤"
  }, {
    "member_id": "9770229",
    "name": "정병국"
  }, {
    "member_id": "9770881",
    "name": "정성호"
  }, {
    "member_id": "9770928",
    "name": "정양석"
  }, {
    "member_id": "9770907",
    "name": "정용기"
  }, {
    "member_id": "9770847",
    "name": "정우택"
  }, {
    "member_id": "9771012",
    "name": "정운천"
  }, {
    "member_id": "9771020",
    "name": "정인화"
  }, {
    "member_id": "9771006",
    "name": "정진석"
  }, {
    "member_id": "9771068",
    "name": "정춘숙"
  }, {
    "member_id": "9771064",
    "name": "제윤경"
  }, {
    "member_id": "9770456",
    "name": "조정식"
  }, {
    "member_id": "9771052",
    "name": "조훈현"
  }, {
    "member_id": "9770458",
    "name": "주승용"
  }, {
    "member_id": "9770883",
    "name": "주호영"
  }, {
    "member_id": "9770925",
    "name": "지상욱"
  }, {
    "member_id": "9770920",
    "name": "천정배"
  }, {
    "member_id": "9771027",
    "name": "최교일"
  }, {
    "member_id": "9771081",
    "name": "최도자"
  }, {
    "member_id": "9771043",
    "name": "최연혜"
  }, {
    "member_id": "9771059",
    "name": "최운열"
  }, {
    "member_id": "9770952",
    "name": "최인호"
  }, {
    "member_id": "9770962",
    "name": "추경호"
  }, {
    "member_id": "9770994",
    "name": "표창원"
  }, {
    "member_id": "9770477",
    "name": "한선교"
  }, {
    "member_id": "9770860",
    "name": "함진규"
  }, {
    "member_id": "9770862",
    "name": "홍문종"
  }, {
    "member_id": "9770959",
    "name": "홍의락"
  }, {
    "member_id": "9770864",
    "name": "홍익표"
  }, {
    "member_id": "9770665",
    "name": "홍일표"
  }, {
    "member_id": "9770867",
    "name": "황주홍"
  }],
  "members_oppose": [],
  "members_abstain": [{
    "member_id": "9770961",
    "name": "곽대훈"
  }, {
    "member_id": "9770716",
    "name": "김기선"
  }, {
    "member_id": "9771030",
    "name": "박완수"
  }, {
    "member_id": "9770497",
    "name": "유승민"
  }, {
    "member_id": "9771040",
    "name": "이종명"
  }, {
    "member_id": "9770837",
    "name": "이헌승"
  }, {
    "member_id": "9770648",
    "name": "조원진"
  }],
  "result": "원안가결",
  "kind": "법률안",
  "committee": "정무위원회"
}